src/verilog/counters/VCJ4RE/device.v
`define m 4

module VCJmRE ( input clk, output wire tc,
                input ce,  output wire ceo,
                input r,   output reg [`m - 1 : 0]q = 0 );

        assign tc = (q == (1 << `m) - 1) ;
        assign ceo = ce & tc ;

        always @ (posedge clk)
                q <= r ? 0 : ce ? (q << 1) | {3'b000, !q[`m - 1]} : q ;

endmodule

src/verilog/counters/testbenches/VCJ4RE.v
`timescale 1ns / 1ps

module VCJ4RE_tb ;

        initial begin
                $dumpfile("data/trace.vcd") ;
                $dumpvars(0, VCJ4RE_tb) ;
                #128 $finish ;
        end

        reg clk = 0 ;
        always #1 clk <= !clk ;

        reg [3:0]q ;
        wire tc ;
        wire ceo ;

        VCJmRE counter (
                .clk (clk),
                .ce (1),
                .r (0),
                .tc (tc),
                .ceo (ceo),
                .q (q)
        );

endmodule

src/verilog/counters/VCJ4RE/data/trace.vcd
$version Generated by VerilatedVcd $end
$timescale 1ps $end
 $scope module $rootio $end
 $upscope $end
 $scope module VCJ4RE_tb $end
  $var wire 1 # clk $end
  $var wire 4 $ q [3:0] $end
  $var wire 1 % tc $end
  $var wire 1 % ceo $end
  $scope module counter $end
   $var wire 1 # clk $end
   $var wire 1 % tc $end
   $var wire 1 & ce $end
   $var wire 1 % ceo $end
   $var wire 1 ' r $end
   $var wire 4 $ q [3:0] $end
  $upscope $end
 $upscope $end
$enddefinitions $end


#0
0#
b0000 $
0%
1&
0'
#1000
1#
b0001 $
#2000
0#
#3000
1#
b0011 $
#4000
0#
#5000
1#
b0111 $
#6000
0#
#7000
1#
b1111 $
1%
#8000
0#
#9000
1#
b1110 $
0%
#10000
0#
#11000
1#
b1100 $
#12000
0#
#13000
1#
b1000 $
#14000
0#
#15000
1#
b0000 $
#16000
0#
#17000
1#
b0001 $
#18000
0#
#19000
1#
b0011 $
#20000
0#
#21000
1#
b0111 $
#22000
0#
#23000
1#
b1111 $
1%
#24000
0#
#25000
1#
b1110 $
0%
#26000
0#
#27000
1#
b1100 $
#28000
0#
#29000
1#
b1000 $
#30000
0#
#31000
1#
b0000 $
#32000
0#
#33000
1#
b0001 $
#34000
0#
#35000
1#
b0011 $
#36000
0#
#37000
1#
b0111 $
#38000
0#
#39000
1#
b1111 $
1%
#40000
0#
#41000
1#
b1110 $
0%
#42000
0#
#43000
1#
b1100 $
#44000
0#
#45000
1#
b1000 $
#46000
0#
#47000
1#
b0000 $
#48000
0#
#49000
1#
b0001 $
#50000
0#
#51000
1#
b0011 $
#52000
0#
#53000
1#
b0111 $
#54000
0#
#55000
1#
b1111 $
1%
#56000
0#
#57000
1#
b1110 $
0%
#58000
0#
#59000
1#
b1100 $
#60000
0#
#61000
1#
b1000 $
#62000
0#
#63000
1#
b0000 $
#64000
0#
#65000
1#
b0001 $
#66000
0#
#67000
1#
b0011 $
#68000
0#
#69000
1#
b0111 $
#70000
0#
#71000
1#
b1111 $
1%
#72000
0#
#73000
1#
b1110 $
0%
#74000
0#
#75000
1#
b1100 $
#76000
0#
#77000
1#
b1000 $
#78000
0#
#79000
1#
b0000 $
#80000
0#
#81000
1#
b0001 $
#82000
0#
#83000
1#
b0011 $
#84000
0#
#85000
1#
b0111 $
#86000
0#
#87000
1#
b1111 $
1%
#88000
0#
#89000
1#
b1110 $
0%
#90000
0#
#91000
1#
b1100 $
#92000
0#
#93000
1#
b1000 $
#94000
0#
#95000
1#
b0000 $
#96000
0#
#97000
1#
b0001 $
#98000
0#
#99000
1#
b0011 $
#100000
0#
#101000
1#
b0111 $
#102000
0#
#103000
1#
b1111 $
1%
#104000
0#
#105000
1#
b1110 $
0%
#106000
0#
#107000
1#
b1100 $
#108000
0#
#109000
1#
b1000 $
#110000
0#
#111000
1#
b0000 $
#112000
0#
#113000
1#
b0001 $
#114000
0#
#115000
1#
b0011 $
#116000
0#
#117000
1#
b0111 $
#118000
0#
#119000
1#
b1111 $
1%
#120000
0#
#121000
1#
b1110 $
0%
#122000
0#
#123000
1#
b1100 $
#124000
0#
#125000
1#
b1000 $
#126000
0#
#127000
1#
b0000 $
