standalone_subprojects/communication_protocols/rs232/supply/URXD1B.v
`timescale 1ns / 1ps
//////////////////////////////////////////////////////////////////////////////////
// Company: 
// Engineer: 
// 
// Create Date:    12:25:50 01/14/2016 
// Design Name: 
// Module Name:    URXD1B 
// Project Name: 
// Target Devices: 
// Tool versions: 
// Description: 
//
// Dependencies: 
//
// Revision: 
// Revision 0.01 - File Created
// Additional Comments: 

////////////////////////////////////////////////////////////////////////////////
module URXD1B(	input Inp,	 output reg en_rx_byte=0,
    				input clk,	 output reg [7:0] sr_dat=0,
									 output reg [3:0]cb_bit=10, 
    					  			 output wire ok_rx_byte,
									 output wire start,									  
									 output wire T_dat,
									 output wire ce_tact,
									 output wire ce_bit,
									 output wire T_start,
									 output wire T_stop,
									 output reg RXD=1
									  );									  
parameter Fclk=50000000 ; //50 MHz
parameter VEL = 115200 ; //115.2 kBod (из таблицы 1 вариантов)
parameter Nt = Fclk/VEL ; //434

reg tRXD=1; 
reg [15:0]cb_tact=0 ; 
assign ce_tact = (cb_tact==Nt) ;
wire df_RXD = !RXD & tRXD ;//Спад RXD
assign T_start = (cb_bit==0) ;
assign T_stop = (cb_bit==9) & en_rx_byte ;
assign T_dat = (cb_bit>0) & (cb_bit<9);
assign start = df_RXD & !en_rx_byte ;//
assign ce_bit = (cb_tact==Nt/2);
assign ok_rx_byte = (ce_bit & T_stop & en_rx_byte & RXD);

always @ (posedge clk) begin
RXD <= Inp ; tRXD <= RXD ;
cb_tact <= (start | ce_tact)? 1 : cb_tact+1;  
en_rx_byte <= (T_start & ce_bit & !RXD)? 1 : (T_stop & ce_tact)? 0 : en_rx_byte ;
cb_bit <=  start? 0 : (ce_tact & en_rx_byte)? cb_bit+1 : cb_bit ;
sr_dat <= start? 0 : (ce_bit & T_dat)? sr_dat>>1 | RXD<<7 : sr_dat ;//in
end

endmodule

standalone_subprojects/communication_protocols/rs232/supply/UTXD1B.v
`timescale 1ns / 1ps
////////////////////////////////////////////////////////////////////////////////
// Company: 
// Engineer:
//
// Create Date:    14:58:52 09/28/11
// Design Name:    
// Module Name:    UTXD1B
// Project Name:   
// Target Device:  
// Tool versions:  
// Description:
//
// Dependencies:
// 
// Revision:
// Revision 0.01 - File Created
// Additional Comments:
module UTXD1B(	input clk,		output wire TXD,//Выход 
    				input[7:0]dat,	output wire ce_tact,//Строб такта
    				input st,		output reg en_tx_byte=0,//Интервал передачи
										output reg [3:0] cb_bit=0, 
										output wire T_start,//Старт такт
										output wire T_dat,//Интервал данных
										output wire T_stop,//Стоп такт
										output wire ce_stop,//Конец кадра
										output reg [7:0] sr_dat=0//Регистр сдвига данных
										 );
										 
parameter Fclk=50000000 ; //50 MHz
parameter VEL = 115200 ; //115.2 kBod (из таблицы 1 вариантов)
parameter Nt = Fclk/VEL ; //434

reg [15:0]cb_tact=0 ;							//Счетчик такта 	
assign ce_tact = (cb_tact==Nt) ;				//Строб такта
assign T_start=((cb_bit==0) & en_tx_byte);//Старт такт  
assign T_dat = (cb_bit<9) & (cb_bit>0);	//Интервал данных
assign T_stop = (cb_bit==9) ;					//Стоп такт
assign ce_stop = T_stop & ce_tact ;			//Строб стопа
assign TXD = T_start? 0 : T_dat? sr_dat[0] : 1 ;//Последовательные данные
wire start = st & !en_tx_byte ;
always @ (posedge clk) begin
cb_tact <= (start | ce_tact)? 1 : cb_tact+1 ;
en_tx_byte  <= st? 1 : ce_stop? 0 : en_tx_byte ; 
cb_bit <= start? 0 : (ce_tact & en_tx_byte)? cb_bit+1 : cb_bit ;
sr_dat <= (T_start & ce_tact)? dat : (T_dat & ce_tact)? sr_dat>>1 : sr_dat ; 
end
endmodule

standalone_subprojects/communication_protocols/rs232/modules/Sch_test_URXD1B.v
`timescale 1ns / 1ps
      
module Sch_test_URXD1B(	input tx_clk,	   output wire TXD,
    			input st,	   output wire [3:0] cb_bit_tx,
			input[7:0]tx_dat,  output wire en_rx_byte,
    			input rx_clk,	   output wire [7:0] sr_dat,
					   output wire [3:0] cb_bit_rx,
					   output wire ok_rx_byte,
					   output wire start_rx,
					   output wire T_start,
					   output wire T_dat,
					   output wire T_stop,
					   output wire ce_tact,
					   output wire ce_bit,
					   output wire RXD );
														
        UTXD1B DD1 (
                .clk(tx_clk),
                .TXD(TXD),
		.dat(tx_dat),
                .cb_bit(cb_bit_tx),
		.st(st)
        );								
											   
        URXD1B DD2 (
                .Inp(TXD),
                .en_rx_byte(en_rx_byte),
    		.clk(rx_clk),
                .sr_dat(sr_dat),
		.cb_bit(cb_bit_rx),
    		.ok_rx_byte(ok_rx_byte),
		.start(start_rx),
		.T_start(T_start),
		.T_dat(T_dat),
		.T_stop(T_stop),
		.ce_tact(ce_tact),
		.ce_bit(ce_bit),
		.RXD(RXD)	
	);

endmodule

standalone_subprojects/communication_protocols/rs232/testbenches/tf1_Sch_test_URXD1B.v
`timescale 1ns / 1ps

module tf1_Sch_test_URXD1B;

	reg tx_clk;
	reg st;
	reg [7:0] tx_dat;
	reg rx_clk;

	wire TXD;
	wire RXD;
	wire [3:0] cb_bit_tx;
	wire en_rx_byte;
	wire [7:0] sr_dat;
	wire [3:0] cb_bit_rx;
	wire ok_rx_byte;
	wire start_rx;
	wire T_start;
	wire T_dat;
	wire T_stop;
	wire ce_tact;
	wire ce_bit;

	Sch_test_URXD1B uut (
		.tx_clk(tx_clk), 
		.TXD(TXD),
		.RXD(RXD),
		.st(st), 
		.cb_bit_tx(cb_bit_tx), 
		.tx_dat(tx_dat), 
		.en_rx_byte(en_rx_byte), 
		.rx_clk(rx_clk), 
		.sr_dat(sr_dat),
		.cb_bit_rx(cb_bit_rx),	
		.ok_rx_byte(ok_rx_byte), 
		.start_rx(start_rx), 
		.T_start(T_start), 
		.T_dat(T_dat), 
		.T_stop(T_stop), 
		.ce_tact(ce_tact), 
		.ce_bit(ce_bit)
	);

        always begin tx_clk = 1'b0; #10 tx_clk = 1'b1; #10;  end
        always begin rx_clk = 1'b0; #10 rx_clk = 1'b1; #10;  end

        // always begin rx_clk = 1'b0; #9.5 rx_clk = 1'b1; #9.5;  end
        // always begin rx_clk = 1'b0; #10.5 rx_clk = 1'b1; #10.5;  end

	initial begin
                $dumpfile("rs232.vcd");
                $dumpvars(0, tf1_Sch_test_URXD1B);

		st = 0;	tx_dat = 0;
                #10; st = 1; tx_dat = 8'b10010010;
                #20; st = 0; tx_dat = 8'b10010010;

                #150000; $finish;
	end
      
endmodule

standalone_subprojects/communication_protocols/rs232/rs232.vcd
$version Generated by VerilatedVcd $end
$timescale 1ps $end
 $scope module $rootio $end
 $upscope $end
 $scope module tf1_Sch_test_URXD1B $end
  $var wire 1 ; tx_clk $end
  $var wire 1 < st $end
  $var wire 8 = tx_dat [7:0] $end
  $var wire 1 > rx_clk $end
  $var wire 1 1 TXD $end
  $var wire 1 # RXD $end
  $var wire 4 2 cb_bit_tx [3:0] $end
  $var wire 1 $ en_rx_byte $end
  $var wire 8 % sr_dat [7:0] $end
  $var wire 4 & cb_bit_rx [3:0] $end
  $var wire 1 ' ok_rx_byte $end
  $var wire 1 ( start_rx $end
  $var wire 1 ) T_start $end
  $var wire 1 * T_dat $end
  $var wire 1 + T_stop $end
  $var wire 1 , ce_tact $end
  $var wire 1 - ce_bit $end
  $scope module uut $end
   $var wire 1 ; tx_clk $end
   $var wire 1 1 TXD $end
   $var wire 1 < st $end
   $var wire 4 2 cb_bit_tx [3:0] $end
   $var wire 8 = tx_dat [7:0] $end
   $var wire 1 $ en_rx_byte $end
   $var wire 1 > rx_clk $end
   $var wire 8 % sr_dat [7:0] $end
   $var wire 4 & cb_bit_rx [3:0] $end
   $var wire 1 ' ok_rx_byte $end
   $var wire 1 ( start_rx $end
   $var wire 1 ) T_start $end
   $var wire 1 * T_dat $end
   $var wire 1 + T_stop $end
   $var wire 1 , ce_tact $end
   $var wire 1 - ce_bit $end
   $var wire 1 # RXD $end
   $scope module DD1 $end
    $var wire 1 ; clk $end
    $var wire 1 1 TXD $end
    $var wire 8 = dat [7:0] $end
    $var wire 1 3 ce_tact $end
    $var wire 1 < st $end
    $var wire 1 4 en_tx_byte $end
    $var wire 4 2 cb_bit [3:0] $end
    $var wire 1 5 T_start $end
    $var wire 1 6 T_dat $end
    $var wire 1 7 T_stop $end
    $var wire 1 8 ce_stop $end
    $var wire 8 9 sr_dat [7:0] $end
    $var wire 32 @ Fclk [31:0] $end
    $var wire 32 A VEL [31:0] $end
    $var wire 32 B Nt [31:0] $end
    $var wire 16 : cb_tact [15:0] $end
    $var wire 1 ? start $end
   $upscope $end
   $scope module DD2 $end
    $var wire 1 1 Inp $end
    $var wire 1 $ en_rx_byte $end
    $var wire 1 > clk $end
    $var wire 8 % sr_dat [7:0] $end
    $var wire 4 & cb_bit [3:0] $end
    $var wire 1 ' ok_rx_byte $end
    $var wire 1 ( start $end
    $var wire 1 * T_dat $end
    $var wire 1 , ce_tact $end
    $var wire 1 - ce_bit $end
    $var wire 1 ) T_start $end
    $var wire 1 + T_stop $end
    $var wire 1 # RXD $end
    $var wire 32 @ Fclk [31:0] $end
    $var wire 32 A VEL [31:0] $end
    $var wire 32 B Nt [31:0] $end
    $var wire 1 . tRXD $end
    $var wire 16 / cb_tact [15:0] $end
    $var wire 1 0 df_RXD $end
   $upscope $end
  $upscope $end
 $upscope $end
$enddefinitions $end


#0
1#
0$
b00000000 %
b1010 &
0'
0(
0)
0*
0+
0,
0-
1.
b0000000000000000 /
00
11
b0000 2
03
04
05
06
07
08
b00000000 9
b0000000000000000 :
0;
0<
b00000000 =
0>
0?
b00000001100110111111110011000000 @
b00000000000000001110000100000000 A
b00000000000000000000000111010100 B
#10000
b0000000000000001 /
01
14
15
b0000000000000001 :
1;
1<
b10010010 =
1>
#20000
0;
0>
#30000
0#
1(
b0000000000000010 /
10
b0000000000000010 :
1;
0<
1>
#40000
0;
0>
#50000
b0000 &
0(
1)
0.
b0000000000000001 /
00
b0000000000000011 :
1;
1>
#60000
0;
0>
#70000
b0000000000000010 /
b0000000000000100 :
1;
1>
#80000
0;
0>
#90000
b0000000000000011 /
b0000000000000101 :
1;
1>
#100000
0;
0>
#110000
b0000000000000100 /
b0000000000000110 :
1;
1>
#120000
0;
0>
#130000
b0000000000000101 /
b0000000000000111 :
1;
1>
#140000
0;
0>
#150000
b0000000000000110 /
b0000000000001000 :
1;
1>
#160000
0;
0>
#170000
b0000000000000111 /
b0000000000001001 :
1;
1>
#180000
0;
0>
#190000
b0000000000001000 /
b0000000000001010 :
1;
1>
#200000
0;
0>
#210000
b0000000000001001 /
b0000000000001011 :
1;
1>
#220000
0;
0>
#230000
b0000000000001010 /
b0000000000001100 :
1;
1>
#240000
0;
0>
#250000
b0000000000001011 /
b0000000000001101 :
1;
1>
#260000
0;
0>
#270000
b0000000000001100 /
b0000000000001110 :
1;
1>
#280000
0;
0>
#290000
b0000000000001101 /
b0000000000001111 :
1;
1>
#300000
0;
0>
#310000
b0000000000001110 /
b0000000000010000 :
1;
1>
#320000
0;
0>
#330000
b0000000000001111 /
b0000000000010001 :
1;
1>
#340000
0;
0>
#350000
b0000000000010000 /
b0000000000010010 :
1;
1>
#360000
0;
0>
#370000
b0000000000010001 /
b0000000000010011 :
1;
1>
#380000
0;
0>
#390000
b0000000000010010 /
b0000000000010100 :
1;
1>
#400000
0;
0>
#410000
b0000000000010011 /
b0000000000010101 :
1;
1>
#420000
0;
0>
#430000
b0000000000010100 /
b0000000000010110 :
1;
1>
#440000
0;
0>
#450000
b0000000000010101 /
b0000000000010111 :
1;
1>
#460000
0;
0>
#470000
b0000000000010110 /
b0000000000011000 :
1;
1>
#480000
0;
0>
#490000
b0000000000010111 /
b0000000000011001 :
1;
1>
#500000
0;
0>
#510000
b0000000000011000 /
b0000000000011010 :
1;
1>
#520000
0;
0>
#530000
b0000000000011001 /
b0000000000011011 :
1;
1>
#540000
0;
0>
#550000
b0000000000011010 /
b0000000000011100 :
1;
1>
#560000
0;
0>
#570000
b0000000000011011 /
b0000000000011101 :
1;
1>
#580000
0;
0>
#590000
b0000000000011100 /
b0000000000011110 :
1;
1>
#600000
0;
0>
#610000
b0000000000011101 /
b0000000000011111 :
1;
1>
#620000
0;
0>
#630000
b0000000000011110 /
b0000000000100000 :
1;
1>
#640000
0;
0>
#650000
b0000000000011111 /
b0000000000100001 :
1;
1>
#660000
0;
0>
#670000
b0000000000100000 /
b0000000000100010 :
1;
1>
#680000
0;
0>
#690000
b0000000000100001 /
b0000000000100011 :
1;
1>
#700000
0;
0>
#710000
b0000000000100010 /
b0000000000100100 :
1;
1>
#720000
0;
0>
#730000
b0000000000100011 /
b0000000000100101 :
1;
1>
#740000
0;
0>
#750000
b0000000000100100 /
b0000000000100110 :
1;
1>
#760000
0;
0>
#770000
b0000000000100101 /
b0000000000100111 :
1;
1>
#780000
0;
0>
#790000
b0000000000100110 /
b0000000000101000 :
1;
1>
#800000
0;
0>
#810000
b0000000000100111 /
b0000000000101001 :
1;
1>
#820000
0;
0>
#830000
b0000000000101000 /
b0000000000101010 :
1;
1>
#840000
0;
0>
#850000
b0000000000101001 /
b0000000000101011 :
1;
1>
#860000
0;
0>
#870000
b0000000000101010 /
b0000000000101100 :
1;
1>
#880000
0;
0>
#890000
b0000000000101011 /
b0000000000101101 :
1;
1>
#900000
0;
0>
#910000
b0000000000101100 /
b0000000000101110 :
1;
1>
#920000
0;
0>
#930000
b0000000000101101 /
b0000000000101111 :
1;
1>
#940000
0;
0>
#950000
b0000000000101110 /
b0000000000110000 :
1;
1>
#960000
0;
0>
#970000
b0000000000101111 /
b0000000000110001 :
1;
1>
#980000
0;
0>
#990000
b0000000000110000 /
b0000000000110010 :
1;
1>
#1000000
0;
0>
#1010000
b0000000000110001 /
b0000000000110011 :
1;
1>
#1020000
0;
0>
#1030000
b0000000000110010 /
b0000000000110100 :
1;
1>
#1040000
0;
0>
#1050000
b0000000000110011 /
b0000000000110101 :
1;
1>
#1060000
0;
0>
#1070000
b0000000000110100 /
b0000000000110110 :
1;
1>
#1080000
0;
0>
#1090000
b0000000000110101 /
b0000000000110111 :
1;
1>
#1100000
0;
0>
#1110000
b0000000000110110 /
b0000000000111000 :
1;
1>
#1120000
0;
0>
#1130000
b0000000000110111 /
b0000000000111001 :
1;
1>
#1140000
0;
0>
#1150000
b0000000000111000 /
b0000000000111010 :
1;
1>
#1160000
0;
0>
#1170000
b0000000000111001 /
b0000000000111011 :
1;
1>
#1180000
0;
0>
#1190000
b0000000000111010 /
b0000000000111100 :
1;
1>
#1200000
0;
0>
#1210000
b0000000000111011 /
b0000000000111101 :
1;
1>
#1220000
0;
0>
#1230000
b0000000000111100 /
b0000000000111110 :
1;
1>
#1240000
0;
0>
#1250000
b0000000000111101 /
b0000000000111111 :
1;
1>
#1260000
0;
0>
#1270000
b0000000000111110 /
b0000000001000000 :
1;
1>
#1280000
0;
0>
#1290000
b0000000000111111 /
b0000000001000001 :
1;
1>
#1300000
0;
0>
#1310000
b0000000001000000 /
b0000000001000010 :
1;
1>
#1320000
0;
0>
#1330000
b0000000001000001 /
b0000000001000011 :
1;
1>
#1340000
0;
0>
#1350000
b0000000001000010 /
b0000000001000100 :
1;
1>
#1360000
0;
0>
#1370000
b0000000001000011 /
b0000000001000101 :
1;
1>
#1380000
0;
0>
#1390000
b0000000001000100 /
b0000000001000110 :
1;
1>
#1400000
0;
0>
#1410000
b0000000001000101 /
b0000000001000111 :
1;
1>
#1420000
0;
0>
#1430000
b0000000001000110 /
b0000000001001000 :
1;
1>
#1440000
0;
0>
#1450000
b0000000001000111 /
b0000000001001001 :
1;
1>
#1460000
0;
0>
#1470000
b0000000001001000 /
b0000000001001010 :
1;
1>
#1480000
0;
0>
#1490000
b0000000001001001 /
b0000000001001011 :
1;
1>
#1500000
0;
0>
#1510000
b0000000001001010 /
b0000000001001100 :
1;
1>
#1520000
0;
0>
#1530000
b0000000001001011 /
b0000000001001101 :
1;
1>
#1540000
0;
0>
#1550000
b0000000001001100 /
b0000000001001110 :
1;
1>
#1560000
0;
0>
#1570000
b0000000001001101 /
b0000000001001111 :
1;
1>
#1580000
0;
0>
#1590000
b0000000001001110 /
b0000000001010000 :
1;
1>
#1600000
0;
0>
#1610000
b0000000001001111 /
b0000000001010001 :
1;
1>
#1620000
0;
0>
#1630000
b0000000001010000 /
b0000000001010010 :
1;
1>
#1640000
0;
0>
#1650000
b0000000001010001 /
b0000000001010011 :
1;
1>
#1660000
0;
0>
#1670000
b0000000001010010 /
b0000000001010100 :
1;
1>
#1680000
0;
0>
#1690000
b0000000001010011 /
b0000000001010101 :
1;
1>
#1700000
0;
0>
#1710000
b0000000001010100 /
b0000000001010110 :
1;
1>
#1720000
0;
0>
#1730000
b0000000001010101 /
b0000000001010111 :
1;
1>
#1740000
0;
0>
#1750000
b0000000001010110 /
b0000000001011000 :
1;
1>
#1760000
0;
0>
#1770000
b0000000001010111 /
b0000000001011001 :
1;
1>
#1780000
0;
0>
#1790000
b0000000001011000 /
b0000000001011010 :
1;
1>
#1800000
0;
0>
#1810000
b0000000001011001 /
b0000000001011011 :
1;
1>
#1820000
0;
0>
#1830000
b0000000001011010 /
b0000000001011100 :
1;
1>
#1840000
0;
0>
#1850000
b0000000001011011 /
b0000000001011101 :
1;
1>
#1860000
0;
0>
#1870000
b0000000001011100 /
b0000000001011110 :
1;
1>
#1880000
0;
0>
#1890000
b0000000001011101 /
b0000000001011111 :
1;
1>
#1900000
0;
0>
#1910000
b0000000001011110 /
b0000000001100000 :
1;
1>
#1920000
0;
0>
#1930000
b0000000001011111 /
b0000000001100001 :
1;
1>
#1940000
0;
0>
#1950000
b0000000001100000 /
b0000000001100010 :
1;
1>
#1960000
0;
0>
#1970000
b0000000001100001 /
b0000000001100011 :
1;
1>
#1980000
0;
0>
#1990000
b0000000001100010 /
b0000000001100100 :
1;
1>
#2000000
0;
0>
#2010000
b0000000001100011 /
b0000000001100101 :
1;
1>
#2020000
0;
0>
#2030000
b0000000001100100 /
b0000000001100110 :
1;
1>
#2040000
0;
0>
#2050000
b0000000001100101 /
b0000000001100111 :
1;
1>
#2060000
0;
0>
#2070000
b0000000001100110 /
b0000000001101000 :
1;
1>
#2080000
0;
0>
#2090000
b0000000001100111 /
b0000000001101001 :
1;
1>
#2100000
0;
0>
#2110000
b0000000001101000 /
b0000000001101010 :
1;
1>
#2120000
0;
0>
#2130000
b0000000001101001 /
b0000000001101011 :
1;
1>
#2140000
0;
0>
#2150000
b0000000001101010 /
b0000000001101100 :
1;
1>
#2160000
0;
0>
#2170000
b0000000001101011 /
b0000000001101101 :
1;
1>
#2180000
0;
0>
#2190000
b0000000001101100 /
b0000000001101110 :
1;
1>
#2200000
0;
0>
#2210000
b0000000001101101 /
b0000000001101111 :
1;
1>
#2220000
0;
0>
#2230000
b0000000001101110 /
b0000000001110000 :
1;
1>
#2240000
0;
0>
#2250000
b0000000001101111 /
b0000000001110001 :
1;
1>
#2260000
0;
0>
#2270000
b0000000001110000 /
b0000000001110010 :
1;
1>
#2280000
0;
0>
#2290000
b0000000001110001 /
b0000000001110011 :
1;
1>
#2300000
0;
0>
#2310000
b0000000001110010 /
b0000000001110100 :
1;
1>
#2320000
0;
0>
#2330000
b0000000001110011 /
b0000000001110101 :
1;
1>
#2340000
0;
0>
#2350000
b0000000001110100 /
b0000000001110110 :
1;
1>
#2360000
0;
0>
#2370000
b0000000001110101 /
b0000000001110111 :
1;
1>
#2380000
0;
0>
#2390000
b0000000001110110 /
b0000000001111000 :
1;
1>
#2400000
0;
0>
#2410000
b0000000001110111 /
b0000000001111001 :
1;
1>
#2420000
0;
0>
#2430000
b0000000001111000 /
b0000000001111010 :
1;
1>
#2440000
0;
0>
#2450000
b0000000001111001 /
b0000000001111011 :
1;
1>
#2460000
0;
0>
#2470000
b0000000001111010 /
b0000000001111100 :
1;
1>
#2480000
0;
0>
#2490000
b0000000001111011 /
b0000000001111101 :
1;
1>
#2500000
0;
0>
#2510000
b0000000001111100 /
b0000000001111110 :
1;
1>
#2520000
0;
0>
#2530000
b0000000001111101 /
b0000000001111111 :
1;
1>
#2540000
0;
0>
#2550000
b0000000001111110 /
b0000000010000000 :
1;
1>
#2560000
0;
0>
#2570000
b0000000001111111 /
b0000000010000001 :
1;
1>
#2580000
0;
0>
#2590000
b0000000010000000 /
b0000000010000010 :
1;
1>
#2600000
0;
0>
#2610000
b0000000010000001 /
b0000000010000011 :
1;
1>
#2620000
0;
0>
#2630000
b0000000010000010 /
b0000000010000100 :
1;
1>
#2640000
0;
0>
#2650000
b0000000010000011 /
b0000000010000101 :
1;
1>
#2660000
0;
0>
#2670000
b0000000010000100 /
b0000000010000110 :
1;
1>
#2680000
0;
0>
#2690000
b0000000010000101 /
b0000000010000111 :
1;
1>
#2700000
0;
0>
#2710000
b0000000010000110 /
b0000000010001000 :
1;
1>
#2720000
0;
0>
#2730000
b0000000010000111 /
b0000000010001001 :
1;
1>
#2740000
0;
0>
#2750000
b0000000010001000 /
b0000000010001010 :
1;
1>
#2760000
0;
0>
#2770000
b0000000010001001 /
b0000000010001011 :
1;
1>
#2780000
0;
0>
#2790000
b0000000010001010 /
b0000000010001100 :
1;
1>
#2800000
0;
0>
#2810000
b0000000010001011 /
b0000000010001101 :
1;
1>
#2820000
0;
0>
#2830000
b0000000010001100 /
b0000000010001110 :
1;
1>
#2840000
0;
0>
#2850000
b0000000010001101 /
b0000000010001111 :
1;
1>
#2860000
0;
0>
#2870000
b0000000010001110 /
b0000000010010000 :
1;
1>
#2880000
0;
0>
#2890000
b0000000010001111 /
b0000000010010001 :
1;
1>
#2900000
0;
0>
#2910000
b0000000010010000 /
b0000000010010010 :
1;
1>
#2920000
0;
0>
#2930000
b0000000010010001 /
b0000000010010011 :
1;
1>
#2940000
0;
0>
#2950000
b0000000010010010 /
b0000000010010100 :
1;
1>
#2960000
0;
0>
#2970000
b0000000010010011 /
b0000000010010101 :
1;
1>
#2980000
0;
0>
#2990000
b0000000010010100 /
b0000000010010110 :
1;
1>
#3000000
0;
0>
#3010000
b0000000010010101 /
b0000000010010111 :
1;
1>
#3020000
0;
0>
#3030000
b0000000010010110 /
b0000000010011000 :
1;
1>
#3040000
0;
0>
#3050000
b0000000010010111 /
b0000000010011001 :
1;
1>
#3060000
0;
0>
#3070000
b0000000010011000 /
b0000000010011010 :
1;
1>
#3080000
0;
0>
#3090000
b0000000010011001 /
b0000000010011011 :
1;
1>
#3100000
0;
0>
#3110000
b0000000010011010 /
b0000000010011100 :
1;
1>
#3120000
0;
0>
#3130000
b0000000010011011 /
b0000000010011101 :
1;
1>
#3140000
0;
0>
#3150000
b0000000010011100 /
b0000000010011110 :
1;
1>
#3160000
0;
0>
#3170000
b0000000010011101 /
b0000000010011111 :
1;
1>
#3180000
0;
0>
#3190000
b0000000010011110 /
b0000000010100000 :
1;
1>
#3200000
0;
0>
#3210000
b0000000010011111 /
b0000000010100001 :
1;
1>
#3220000
0;
0>
#3230000
b0000000010100000 /
b0000000010100010 :
1;
1>
#3240000
0;
0>
#3250000
b0000000010100001 /
b0000000010100011 :
1;
1>
#3260000
0;
0>
#3270000
b0000000010100010 /
b0000000010100100 :
1;
1>
#3280000
0;
0>
#3290000
b0000000010100011 /
b0000000010100101 :
1;
1>
#3300000
0;
0>
#3310000
b0000000010100100 /
b0000000010100110 :
1;
1>
#3320000
0;
0>
#3330000
b0000000010100101 /
b0000000010100111 :
1;
1>
#3340000
0;
0>
#3350000
b0000000010100110 /
b0000000010101000 :
1;
1>
#3360000
0;
0>
#3370000
b0000000010100111 /
b0000000010101001 :
1;
1>
#3380000
0;
0>
#3390000
b0000000010101000 /
b0000000010101010 :
1;
1>
#3400000
0;
0>
#3410000
b0000000010101001 /
b0000000010101011 :
1;
1>
#3420000
0;
0>
#3430000
b0000000010101010 /
b0000000010101100 :
1;
1>
#3440000
0;
0>
#3450000
b0000000010101011 /
b0000000010101101 :
1;
1>
#3460000
0;
0>
#3470000
b0000000010101100 /
b0000000010101110 :
1;
1>
#3480000
0;
0>
#3490000
b0000000010101101 /
b0000000010101111 :
1;
1>
#3500000
0;
0>
#3510000
b0000000010101110 /
b0000000010110000 :
1;
1>
#3520000
0;
0>
#3530000
b0000000010101111 /
b0000000010110001 :
1;
1>
#3540000
0;
0>
#3550000
b0000000010110000 /
b0000000010110010 :
1;
1>
#3560000
0;
0>
#3570000
b0000000010110001 /
b0000000010110011 :
1;
1>
#3580000
0;
0>
#3590000
b0000000010110010 /
b0000000010110100 :
1;
1>
#3600000
0;
0>
#3610000
b0000000010110011 /
b0000000010110101 :
1;
1>
#3620000
0;
0>
#3630000
b0000000010110100 /
b0000000010110110 :
1;
1>
#3640000
0;
0>
#3650000
b0000000010110101 /
b0000000010110111 :
1;
1>
#3660000
0;
0>
#3670000
b0000000010110110 /
b0000000010111000 :
1;
1>
#3680000
0;
0>
#3690000
b0000000010110111 /
b0000000010111001 :
1;
1>
#3700000
0;
0>
#3710000
b0000000010111000 /
b0000000010111010 :
1;
1>
#3720000
0;
0>
#3730000
b0000000010111001 /
b0000000010111011 :
1;
1>
#3740000
0;
0>
#3750000
b0000000010111010 /
b0000000010111100 :
1;
1>
#3760000
0;
0>
#3770000
b0000000010111011 /
b0000000010111101 :
1;
1>
#3780000
0;
0>
#3790000
b0000000010111100 /
b0000000010111110 :
1;
1>
#3800000
0;
0>
#3810000
b0000000010111101 /
b0000000010111111 :
1;
1>
#3820000
0;
0>
#3830000
b0000000010111110 /
b0000000011000000 :
1;
1>
#3840000
0;
0>
#3850000
b0000000010111111 /
b0000000011000001 :
1;
1>
#3860000
0;
0>
#3870000
b0000000011000000 /
b0000000011000010 :
1;
1>
#3880000
0;
0>
#3890000
b0000000011000001 /
b0000000011000011 :
1;
1>
#3900000
0;
0>
#3910000
b0000000011000010 /
b0000000011000100 :
1;
1>
#3920000
0;
0>
#3930000
b0000000011000011 /
b0000000011000101 :
1;
1>
#3940000
0;
0>
#3950000
b0000000011000100 /
b0000000011000110 :
1;
1>
#3960000
0;
0>
#3970000
b0000000011000101 /
b0000000011000111 :
1;
1>
#3980000
0;
0>
#3990000
b0000000011000110 /
b0000000011001000 :
1;
1>
#4000000
0;
0>
#4010000
b0000000011000111 /
b0000000011001001 :
1;
1>
#4020000
0;
0>
#4030000
b0000000011001000 /
b0000000011001010 :
1;
1>
#4040000
0;
0>
#4050000
b0000000011001001 /
b0000000011001011 :
1;
1>
#4060000
0;
0>
#4070000
b0000000011001010 /
b0000000011001100 :
1;
1>
#4080000
0;
0>
#4090000
b0000000011001011 /
b0000000011001101 :
1;
1>
#4100000
0;
0>
#4110000
b0000000011001100 /
b0000000011001110 :
1;
1>
#4120000
0;
0>
#4130000
b0000000011001101 /
b0000000011001111 :
1;
1>
#4140000
0;
0>
#4150000
b0000000011001110 /
b0000000011010000 :
1;
1>
#4160000
0;
0>
#4170000
b0000000011001111 /
b0000000011010001 :
1;
1>
#4180000
0;
0>
#4190000
b0000000011010000 /
b0000000011010010 :
1;
1>
#4200000
0;
0>
#4210000
b0000000011010001 /
b0000000011010011 :
1;
1>
#4220000
0;
0>
#4230000
b0000000011010010 /
b0000000011010100 :
1;
1>
#4240000
0;
0>
#4250000
b0000000011010011 /
b0000000011010101 :
1;
1>
#4260000
0;
0>
#4270000
b0000000011010100 /
b0000000011010110 :
1;
1>
#4280000
0;
0>
#4290000
b0000000011010101 /
b0000000011010111 :
1;
1>
#4300000
0;
0>
#4310000
b0000000011010110 /
b0000000011011000 :
1;
1>
#4320000
0;
0>
#4330000
b0000000011010111 /
b0000000011011001 :
1;
1>
#4340000
0;
0>
#4350000
b0000000011011000 /
b0000000011011010 :
1;
1>
#4360000
0;
0>
#4370000
b0000000011011001 /
b0000000011011011 :
1;
1>
#4380000
0;
0>
#4390000
b0000000011011010 /
b0000000011011100 :
1;
1>
#4400000
0;
0>
#4410000
b0000000011011011 /
b0000000011011101 :
1;
1>
#4420000
0;
0>
#4430000
b0000000011011100 /
b0000000011011110 :
1;
1>
#4440000
0;
0>
#4450000
b0000000011011101 /
b0000000011011111 :
1;
1>
#4460000
0;
0>
#4470000
b0000000011011110 /
b0000000011100000 :
1;
1>
#4480000
0;
0>
#4490000
b0000000011011111 /
b0000000011100001 :
1;
1>
#4500000
0;
0>
#4510000
b0000000011100000 /
b0000000011100010 :
1;
1>
#4520000
0;
0>
#4530000
b0000000011100001 /
b0000000011100011 :
1;
1>
#4540000
0;
0>
#4550000
b0000000011100010 /
b0000000011100100 :
1;
1>
#4560000
0;
0>
#4570000
b0000000011100011 /
b0000000011100101 :
1;
1>
#4580000
0;
0>
#4590000
b0000000011100100 /
b0000000011100110 :
1;
1>
#4600000
0;
0>
#4610000
b0000000011100101 /
b0000000011100111 :
1;
1>
#4620000
0;
0>
#4630000
b0000000011100110 /
b0000000011101000 :
1;
1>
#4640000
0;
0>
#4650000
b0000000011100111 /
b0000000011101001 :
1;
1>
#4660000
0;
0>
#4670000
b0000000011101000 /
b0000000011101010 :
1;
1>
#4680000
0;
0>
#4690000
b0000000011101001 /
b0000000011101011 :
1;
1>
#4700000
0;
0>
#4710000
1-
b0000000011101010 /
b0000000011101100 :
1;
1>
#4720000
0;
0>
#4730000
1$
0-
b0000000011101011 /
b0000000011101101 :
1;
1>
#4740000
0;
0>
#4750000
b0000000011101100 /
b0000000011101110 :
1;
1>
#4760000
0;
0>
#4770000
b0000000011101101 /
b0000000011101111 :
1;
1>
#4780000
0;
0>
#4790000
b0000000011101110 /
b0000000011110000 :
1;
1>
#4800000
0;
0>
#4810000
b0000000011101111 /
b0000000011110001 :
1;
1>
#4820000
0;
0>
#4830000
b0000000011110000 /
b0000000011110010 :
1;
1>
#4840000
0;
0>
