src/verilog/counters/modules/VCB4CLED.v
`define m 4

module VCBmCLED( input clk,           output wire tc,
                 input ce,            output wire ceo,
                 input clr,           output reg [`m - 1 : 0]q = 0,
                 input up,
                 input l,
                 input [`m - 1 : 0]di );

        assign tc = up ? (q == (1 << `m) - 1) : (q == 0) ;
        assign ceo = ce & tc ;

        always @ (posedge clr or posedge clk) begin
                if (clr) q <= 0 ;
                else q <= l ? di : (up & ce) ? q + 1 : (!up & ce) ? q - 1 : q ;
        end

endmodule

src/verilog/counters/testbenches/VCB4CLED.v
`timescale 1ns / 1ps

module VCBmCLED_tb ;

        initial begin
                $dumpfile("data/trace.vcd") ;
                $dumpvars(0, VCBmCLED_tb) ;
                #256 $finish ;
        end

        /* single load test */
        reg l = 0 ;
        initial begin
                #8 l = 1 ; // random load moment
                #2 l = 0 ; // hold "load" for 1 tick
        end

        reg clk = 0 ;
        always #1 clk <= !clk ;

        reg up = 0 ;
        always #64 up <= !up ; // change direction periodically

        reg [3:0]q ;
        wire tc ;
        wire ceo ;

        VCBmCLED counter (
                .clk (clk),
                .ce (1),
                .clr (0),
                .up (up),
                .l (l),
                .di (4'b0100), // random loaded value
                .tc (tc),
                .ceo (ceo),
                .q (q)
        );

endmodule

src/verilog/counters/VCB4CLED/data/trace.vcd
$version Generated by VerilatedVcd $end
$timescale 1ps $end
 $scope module $rootio $end
 $upscope $end
 $scope module VCBmCLED_tb $end
  $var wire 1 # l $end
  $var wire 1 $ clk $end
  $var wire 1 % up $end
  $var wire 4 & q [3:0] $end
  $var wire 1 ' tc $end
  $var wire 1 ' ceo $end
  $scope module counter $end
   $var wire 1 $ clk $end
   $var wire 1 ' tc $end
   $var wire 1 ( ce $end
   $var wire 1 ' ceo $end
   $var wire 1 ) clr $end
   $var wire 4 & q [3:0] $end
   $var wire 1 % up $end
   $var wire 1 # l $end
   $var wire 4 * di [3:0] $end
  $upscope $end
 $upscope $end
$enddefinitions $end


#0
0#
0$
0%
b0000 &
1'
1(
0)
b0100 *
#1000
1$
b1111 &
0'
#2000
0$
#3000
1$
b1110 &
#4000
0$
#5000
1$
b1101 &
#6000
0$
#7000
1$
b1100 &
#8000
1#
0$
#9000
1$
b0100 &
#10000
0#
0$
#11000
1$
b0011 &
#12000
0$
#13000
1$
b0010 &
#14000
0$
#15000
1$
b0001 &
#16000
0$
#17000
1$
b0000 &
1'
#18000
0$
#19000
1$
b1111 &
0'
#20000
0$
#21000
1$
b1110 &
#22000
0$
#23000
1$
b1101 &
#24000
0$
#25000
1$
b1100 &
#26000
0$
#27000
1$
b1011 &
#28000
0$
#29000
1$
b1010 &
#30000
0$
#31000
1$
b1001 &
#32000
0$
#33000
1$
b1000 &
#34000
0$
#35000
1$
b0111 &
#36000
0$
#37000
1$
b0110 &
#38000
0$
#39000
1$
b0101 &
#40000
0$
#41000
1$
b0100 &
#42000
0$
#43000
1$
b0011 &
#44000
0$
#45000
1$
b0010 &
#46000
0$
#47000
1$
b0001 &
#48000
0$
#49000
1$
b0000 &
1'
#50000
0$
#51000
1$
b1111 &
0'
#52000
0$
#53000
1$
b1110 &
#54000
0$
#55000
1$
b1101 &
#56000
0$
#57000
1$
b1100 &
#58000
0$
#59000
1$
b1011 &
#60000
0$
#61000
1$
b1010 &
#62000
0$
#63000
1$
b1001 &
#64000
0$
1%
#65000
1$
b1010 &
#66000
0$
#67000
1$
b1011 &
#68000
0$
#69000
1$
b1100 &
#70000
0$
#71000
1$
b1101 &
#72000
0$
#73000
1$
b1110 &
#74000
0$
#75000
1$
b1111 &
1'
#76000
0$
#77000
1$
b0000 &
0'
#78000
0$
#79000
1$
b0001 &
#80000
0$
#81000
1$
b0010 &
#82000
0$
#83000
1$
b0011 &
#84000
0$
#85000
1$
b0100 &
#86000
0$
#87000
1$
b0101 &
#88000
0$
#89000
1$
b0110 &
#90000
0$
#91000
1$
b0111 &
#92000
0$
#93000
1$
b1000 &
#94000
0$
#95000
1$
b1001 &
#96000
0$
#97000
1$
b1010 &
#98000
0$
#99000
1$
b1011 &
#100000
0$
#101000
1$
b1100 &
#102000
0$
#103000
1$
b1101 &
#104000
0$
#105000
1$
b1110 &
#106000
0$
#107000
1$
b1111 &
1'
#108000
0$
#109000
1$
b0000 &
0'
#110000
0$
#111000
1$
b0001 &
#112000
0$
#113000
1$
b0010 &
#114000
0$
#115000
1$
b0011 &
#116000
0$
#117000
1$
b0100 &
#118000
0$
#119000
1$
b0101 &
#120000
0$
#121000
1$
b0110 &
#122000
0$
#123000
1$
b0111 &
#124000
0$
#125000
1$
b1000 &
#126000
0$
#127000
1$
b1001 &
#128000
0$
0%
#129000
1$
b1000 &
#130000
0$
#131000
1$
b0111 &
#132000
0$
#133000
1$
b0110 &
#134000
0$
#135000
1$
b0101 &
#136000
0$
#137000
1$
b0100 &
#138000
0$
#139000
1$
b0011 &
#140000
0$
#141000
1$
b0010 &
#142000
0$
#143000
1$
b0001 &
#144000
0$
#145000
1$
b0000 &
1'
#146000
0$
#147000
1$
b1111 &
0'
#148000
0$
#149000
1$
b1110 &
#150000
0$
#151000
1$
b1101 &
#152000
0$
#153000
1$
b1100 &
#154000
0$
#155000
1$
b1011 &
#156000
0$
#157000
1$
b1010 &
#158000
0$
#159000
1$
b1001 &
#160000
0$
#161000
1$
b1000 &
#162000
0$
#163000
1$
b0111 &
#164000
0$
#165000
1$
b0110 &
#166000
0$
#167000
1$
b0101 &
#168000
0$
#169000
1$
b0100 &
#170000
0$
#171000
1$
b0011 &
#172000
0$
#173000
1$
b0010 &
#174000
0$
#175000
1$
b0001 &
#176000
0$
#177000
1$
b0000 &
1'
#178000
0$
#179000
1$
b1111 &
0'
#180000
0$
#181000
1$
b1110 &
#182000
0$
#183000
1$
b1101 &
#184000
0$
#185000
1$
b1100 &
#186000
0$
#187000
1$
b1011 &
#188000
0$
#189000
1$
b1010 &
#190000
0$
#191000
1$
b1001 &
#192000
0$
1%
#193000
1$
b1010 &
#194000
0$
#195000
1$
b1011 &
#196000
0$
#197000
1$
b1100 &
#198000
0$
#199000
1$
b1101 &
#200000
0$
#201000
1$
b1110 &
#202000
0$
#203000
1$
b1111 &
1'
#204000
0$
#205000
1$
b0000 &
0'
#206000
0$
#207000
1$
b0001 &
#208000
0$
#209000
1$
b0010 &
#210000
0$
#211000
1$
b0011 &
#212000
0$
#213000
1$
b0100 &
#214000
0$
#215000
1$
b0101 &
#216000
0$
#217000
1$
b0110 &
#218000
0$
#219000
1$
b0111 &
#220000
0$
#221000
1$
b1000 &
#222000
0$
#223000
1$
b1001 &
#224000
0$
#225000
1$
b1010 &
#226000
0$
#227000
1$
b1011 &
#228000
0$
#229000
1$
b1100 &
#230000
0$
#231000
1$
b1101 &
#232000
0$
#233000
1$
b1110 &
#234000
0$
#235000
1$
b1111 &
1'
#236000
0$
#237000
1$
b0000 &
0'
#238000
0$
#239000
1$
b0001 &
#240000
0$
#241000
1$
b0010 &
#242000
0$
#243000
1$
b0011 &
#244000
0$
#245000
1$
b0100 &
#246000
0$
#247000
1$
b0101 &
#248000
0$
#249000
1$
b0110 &
#250000
0$
#251000
1$
b0111 &
#252000
0$
#253000
1$
b1000 &
#254000
0$
#255000
1$
b1001 &
#256000
0$
0%
