standalone_subprojects/communication_protocols/spi/modules/spi_master.v
module spi_master #(
    parameter int CLKFREQ = 27000000,  // 27MHz
    parameter int WIDTH = 15,
    parameter int SPIFREQ = 250000  // 250KHz => 4us
) (
    input st,
    input clk,

    output reg sclk = 0,
    output reg load = 1,
    output wire mosi,
    input miso,

    input [WIDTH-1:0] din,
    output reg [WIDTH-1:0] dout = 0,
    input clr,
    output reg [WIDTH-1:0] sr_mtx = 0,
    output reg [WIDTH-1:0] sr_mrx = 0,
    output reg [7:0] cb_bit = 0,
    output wire ce,
    output wire ce_tact
);
  localparam int NT = CLKFREQ / (2 * SPIFREQ);

  reg [31:0] cb_tact = 0;

  assign ce = (cb_tact == NT - 1);
  assign mosi = sr_mtx[WIDTH-1];
  assign ce_tact = ce & sclk;

  wire start = st & load;

  always @(posedge clk) begin
    load <= st ? 0 : ((cb_bit == WIDTH - 1) & ce_tact) ? 1 : load;
    cb_tact <= (start | ce) ? 0 : cb_tact + 1;
    sclk <= load ? 0 : ce ? !sclk : sclk;
    sr_mtx <= start ? din : ce_tact ? sr_mtx << 1 : sr_mtx;
    cb_bit <= start ? 0 : ce_tact ? cb_bit + 1 : cb_bit;
  end

  always @(posedge sclk) begin
    sr_mrx <= sr_mrx << 1 | miso;
  end

  always @(posedge load) begin
    dout <= sr_mrx;
  end
endmodule

standalone_subprojects/communication_protocols/spi/testbenches/spi_master_tb.v
module spi_master_tb;
  localparam int WIDTH = 15;

  reg clk = 0;
  reg st = 0;

  initial begin
    $dumpfile("spi_master_tb.vcd");
    $dumpvars(0, spi_master_tb);
    #1 st = 1;
    #1 st = 0;
    #1024 $finish;
  end

  always #1 clk = !clk;

  spi_master #(
      .WIDTH  (WIDTH),
      .CLKFREQ(16),
      .SPIFREQ(2)
  ) master (
      .st (st),
      .clk(clk),
      .din(15'b101110010100011)
  );
endmodule

standalone_subprojects/communication_protocols/spi/spi_master_tb.vcd
$version Generated by VerilatedVcd $end
$timescale 1ps $end
 $scope module $rootio $end
 $upscope $end
 $scope module spi_master_tb $end
  $var wire 32 0 WIDTH [31:0] $end
  $var wire 1 + clk $end
  $var wire 1 , st $end
  $scope module master $end
   $var wire 32 1 CLKFREQ [31:0] $end
   $var wire 32 0 WIDTH [31:0] $end
   $var wire 32 2 SPIFREQ [31:0] $end
   $var wire 1 , st $end
   $var wire 1 + clk $end
   $var wire 1 # sclk $end
   $var wire 1 $ load $end
   $var wire 1 % mosi $end
   $var wire 1 3 miso $end
   $var wire 15 4 din [14:0] $end
   $var wire 15 - dout [14:0] $end
   $var wire 1 5 clr $end
   $var wire 15 & sr_mtx [14:0] $end
   $var wire 15 . sr_mrx [14:0] $end
   $var wire 8 ' cb_bit [7:0] $end
   $var wire 1 ( ce $end
   $var wire 1 ) ce_tact $end
   $var wire 32 6 NT [31:0] $end
   $var wire 32 * cb_tact [31:0] $end
   $var wire 1 / start $end
  $upscope $end
 $upscope $end
$enddefinitions $end


#0
0#
1$
0%
b000000000000000 &
b00000000 '
0(
0)
b00000000000000000000000000000000 *
0+
0,
b000000000000000 -
b000000000000000 .
0/
b00000000000000000000000000001111 0
b00000000000000000000000000010000 1
b00000000000000000000000000000010 2
03
b101110010100011 4
05
b00000000000000000000000000000100 6
#1
0$
1%
b101110010100011 &
1+
1,
#2
0+
0,
#3
b00000000000000000000000000000001 *
1+
#4
0+
#5
b00000000000000000000000000000010 *
1+
#6
0+
#7
1(
b00000000000000000000000000000011 *
1+
#8
0+
#9
1#
0(
b00000000000000000000000000000000 *
1+
#10
0+
#11
b00000000000000000000000000000001 *
1+
#12
0+
#13
b00000000000000000000000000000010 *
1+
#14
0+
#15
1(
1)
b00000000000000000000000000000011 *
1+
#16
0+
#17
0#
0%
b011100101000110 &
b00000001 '
0(
0)
b00000000000000000000000000000000 *
1+
#18
0+
#19
b00000000000000000000000000000001 *
1+
#20
0+
#21
b00000000000000000000000000000010 *
1+
#22
0+
#23
1(
b00000000000000000000000000000011 *
1+
#24
0+
#25
1#
0(
b00000000000000000000000000000000 *
1+
#26
0+
#27
b00000000000000000000000000000001 *
1+
#28
0+
#29
b00000000000000000000000000000010 *
1+
#30
0+
#31
1(
1)
b00000000000000000000000000000011 *
1+
#32
0+
#33
0#
1%
b111001010001100 &
b00000010 '
0(
0)
b00000000000000000000000000000000 *
1+
#34
0+
#35
b00000000000000000000000000000001 *
1+
#36
0+
#37
b00000000000000000000000000000010 *
1+
#38
0+
#39
1(
b00000000000000000000000000000011 *
1+
#40
0+
#41
1#
0(
b00000000000000000000000000000000 *
1+
#42
0+
#43
b00000000000000000000000000000001 *
1+
#44
0+
#45
b00000000000000000000000000000010 *
1+
#46
0+
#47
1(
1)
b00000000000000000000000000000011 *
1+
#48
0+
#49
0#
b110010100011000 &
b00000011 '
0(
0)
b00000000000000000000000000000000 *
1+
#50
0+
#51
b00000000000000000000000000000001 *
1+
#52
0+
#53
b00000000000000000000000000000010 *
1+
#54
0+
#55
1(
b00000000000000000000000000000011 *
1+
#56
0+
#57
1#
0(
b00000000000000000000000000000000 *
1+
#58
0+
#59
b00000000000000000000000000000001 *
1+
#60
0+
#61
b00000000000000000000000000000010 *
1+
#62
0+
#63
1(
1)
b00000000000000000000000000000011 *
1+
#64
0+
#65
0#
b100101000110000 &
b00000100 '
0(
0)
b00000000000000000000000000000000 *
1+
#66
0+
#67
b00000000000000000000000000000001 *
1+
#68
0+
#69
b00000000000000000000000000000010 *
1+
#70
0+
#71
1(
b00000000000000000000000000000011 *
1+
#72
0+
#73
1#
0(
b00000000000000000000000000000000 *
1+
#74
0+
#75
b00000000000000000000000000000001 *
1+
#76
0+
#77
b00000000000000000000000000000010 *
1+
#78
0+
#79
1(
1)
b00000000000000000000000000000011 *
1+
#80
0+
#81
0#
0%
b001010001100000 &
b00000101 '
0(
0)
b00000000000000000000000000000000 *
1+
#82
0+
#83
b00000000000000000000000000000001 *
1+
#84
0+
#85
b00000000000000000000000000000010 *
1+
#86
0+
#87
1(
b00000000000000000000000000000011 *
1+
#88
0+
#89
1#
0(
b00000000000000000000000000000000 *
1+
#90
0+
#91
b00000000000000000000000000000001 *
1+
#92
0+
#93
b00000000000000000000000000000010 *
1+
#94
0+
#95
1(
1)
b00000000000000000000000000000011 *
1+
#96
0+
#97
0#
b010100011000000 &
b00000110 '
0(
0)
b00000000000000000000000000000000 *
1+
#98
0+
#99
b00000000000000000000000000000001 *
1+
#100
0+
#101
b00000000000000000000000000000010 *
1+
#102
0+
#103
1(
b00000000000000000000000000000011 *
1+
#104
0+
#105
1#
0(
b00000000000000000000000000000000 *
1+
#106
0+
#107
b00000000000000000000000000000001 *
1+
#108
0+
#109
b00000000000000000000000000000010 *
1+
#110
0+
#111
1(
1)
b00000000000000000000000000000011 *
1+
#112
0+
#113
0#
1%
b101000110000000 &
b00000111 '
0(
0)
b00000000000000000000000000000000 *
1+
#114
0+
#115
b00000000000000000000000000000001 *
1+
#116
0+
#117
b00000000000000000000000000000010 *
1+
#118
0+
#119
1(
b00000000000000000000000000000011 *
1+
#120
0+
#121
1#
0(
b00000000000000000000000000000000 *
1+
#122
0+
#123
b00000000000000000000000000000001 *
1+
#124
0+
#125
b00000000000000000000000000000010 *
1+
#126
0+
#127
1(
1)
b00000000000000000000000000000011 *
1+
#128
0+
#129
0#
0%
b010001100000000 &
b00001000 '
0(
0)
b00000000000000000000000000000000 *
1+
#130
0+
#131
b00000000000000000000000000000001 *
1+
#132
0+
#133
b00000000000000000000000000000010 *
1+
#134
0+
#135
1(
b00000000000000000000000000000011 *
1+
#136
0+
#137
1#
0(
b00000000000000000000000000000000 *
1+
#138
0+
#139
b00000000000000000000000000000001 *
1+
#140
0+
#141
b00000000000000000000000000000010 *
1+
#142
0+
#143
1(
1)
b00000000000000000000000000000011 *
1+
#144
0+
#145
0#
1%
b100011000000000 &
b00001001 '
0(
0)
b00000000000000000000000000000000 *
1+
#146
0+
#147
b00000000000000000000000000000001 *
1+
#148
0+
#149
b00000000000000000000000000000010 *
1+
#150
0+
#151
1(
b00000000000000000000000000000011 *
1+
#152
0+
#153
1#
0(
b00000000000000000000000000000000 *
1+
#154
0+
#155
b00000000000000000000000000000001 *
1+
#156
0+
#157
b00000000000000000000000000000010 *
1+
#158
0+
#159
1(
1)
b00000000000000000000000000000011 *
1+
#160
0+
#161
0#
0%
b000110000000000 &
b00001010 '
0(
0)
b00000000000000000000000000000000 *
1+
#162
0+
#163
b00000000000000000000000000000001 *
1+
#164
0+
#165
b00000000000000000000000000000010 *
1+
#166
0+
#167
1(
b00000000000000000000000000000011 *
1+
#168
0+
#169
1#
0(
b00000000000000000000000000000000 *
1+
#170
0+
#171
b00000000000000000000000000000001 *
1+
#172
0+
#173
b00000000000000000000000000000010 *
1+
#174
0+
#175
1(
1)
b00000000000000000000000000000011 *
1+
#176
0+
#177
0#
b001100000000000 &
b00001011 '
0(
0)
b00000000000000000000000000000000 *
1+
#178
0+
#179
b00000000000000000000000000000001 *
1+
#180
0+
#181
b00000000000000000000000000000010 *
1+
#182
0+
#183
1(
b00000000000000000000000000000011 *
1+
#184
0+
#185
1#
0(
b00000000000000000000000000000000 *
1+
#186
0+
#187
b00000000000000000000000000000001 *
1+
#188
0+
#189
b00000000000000000000000000000010 *
1+
#190
0+
#191
1(
1)
b00000000000000000000000000000011 *
1+
#192
0+
#193
0#
b011000000000000 &
b00001100 '
0(
0)
b00000000000000000000000000000000 *
1+
#194
0+
#195
b00000000000000000000000000000001 *
1+
#196
0+
#197
b00000000000000000000000000000010 *
1+
#198
0+
#199
1(
b00000000000000000000000000000011 *
1+
#200
0+
#201
1#
0(
b00000000000000000000000000000000 *
1+
#202
0+
#203
b00000000000000000000000000000001 *
1+
#204
0+
#205
b00000000000000000000000000000010 *
1+
#206
0+
#207
1(
1)
b00000000000000000000000000000011 *
1+
#208
0+
#209
0#
1%
b110000000000000 &
b00001101 '
0(
0)
b00000000000000000000000000000000 *
1+
#210
0+
#211
b00000000000000000000000000000001 *
1+
#212
0+
#213
b00000000000000000000000000000010 *
1+
#214
0+
#215
1(
b00000000000000000000000000000011 *
1+
#216
0+
#217
1#
0(
b00000000000000000000000000000000 *
1+
#218
0+
#219
b00000000000000000000000000000001 *
1+
#220
0+
#221
b00000000000000000000000000000010 *
1+
#222
0+
#223
1(
1)
b00000000000000000000000000000011 *
1+
#224
0+
#225
0#
b100000000000000 &
b00001110 '
0(
0)
b00000000000000000000000000000000 *
1+
#226
0+
#227
b00000000000000000000000000000001 *
1+
#228
0+
#229
b00000000000000000000000000000010 *
1+
#230
0+
#231
1(
b00000000000000000000000000000011 *
1+
#232
0+
#233
1#
0(
b00000000000000000000000000000000 *
1+
#234
0+
#235
b00000000000000000000000000000001 *
1+
#236
0+
#237
b00000000000000000000000000000010 *
1+
#238
0+
#239
1(
1)
b00000000000000000000000000000011 *
1+
#240
0+
#241
0#
1$
0%
b000000000000000 &
b00001111 '
0(
0)
b00000000000000000000000000000000 *
1+
#242
0+
#243
b00000000000000000000000000000001 *
1+
#244
0+
#245
b00000000000000000000000000000010 *
1+
#246
0+
#247
1(
b00000000000000000000000000000011 *
1+
#248
0+
#249
0(
b00000000000000000000000000000000 *
1+
#250
0+
#251
b00000000000000000000000000000001 *
1+
#252
0+
#253
b00000000000000000000000000000010 *
1+
#254
0+
#255
1(
b00000000000000000000000000000011 *
1+
#256
0+
#257
0(
b00000000000000000000000000000000 *
1+
#258
0+
#259
b00000000000000000000000000000001 *
1+
#260
0+
#261
b00000000000000000000000000000010 *
1+
#262
0+
#263
1(
b00000000000000000000000000000011 *
1+
#264
0+
#265
0(
b00000000000000000000000000000000 *
1+
#266
0+
#267
b00000000000000000000000000000001 *
1+
#268
0+
#269
b00000000000000000000000000000010 *
1+
#270
0+
#271
1(
b00000000000000000000000000000011 *
1+
#272
0+
#273
0(
b00000000000000000000000000000000 *
1+
#274
0+
#275
b00000000000000000000000000000001 *
1+
#276
0+
#277
b00000000000000000000000000000010 *
1+
#278
0+
#279
1(
b00000000000000000000000000000011 *
1+
#280
0+
#281
0(
b00000000000000000000000000000000 *
1+
#282
0+
#283
b00000000000000000000000000000001 *
1+
#284
0+
#285
b00000000000000000000000000000010 *
1+
#286
0+
#287
1(
b00000000000000000000000000000011 *
1+
#288
0+
#289
0(
b00000000000000000000000000000000 *
1+
#290
0+
#291
b00000000000000000000000000000001 *
1+
#292
0+
#293
b00000000000000000000000000000010 *
1+
#294
0+
#295
1(
b00000000000000000000000000000011 *
1+
#296
0+
#297
0(
b00000000000000000000000000000000 *
1+
#298
0+
#299
b00000000000000000000000000000001 *
1+
#300
0+
#301
b00000000000000000000000000000010 *
1+
#302
0+
#303
1(
b00000000000000000000000000000011 *
1+
#304
0+
#305
0(
b00000000000000000000000000000000 *
1+
#306
0+
#307
b00000000000000000000000000000001 *
1+
#308
0+
#309
b00000000000000000000000000000010 *
1+
#310
0+
#311
1(
b00000000000000000000000000000011 *
1+
#312
0+
#313
0(
b00000000000000000000000000000000 *
1+
#314
0+
#315
b00000000000000000000000000000001 *
1+
#316
0+
#317
b00000000000000000000000000000010 *
1+
#318
0+
#319
1(
b00000000000000000000000000000011 *
1+
#320
0+
#321
0(
b00000000000000000000000000000000 *
1+
#322
0+
#323
b00000000000000000000000000000001 *
1+
#324
0+
#325
b00000000000000000000000000000010 *
1+
#326
0+
#327
1(
b00000000000000000000000000000011 *
1+
#328
0+
#329
0(
b00000000000000000000000000000000 *
1+
#330
0+
#331
b00000000000000000000000000000001 *
1+
#332
0+
#333
b00000000000000000000000000000010 *
1+
#334
0+
#335
1(
b00000000000000000000000000000011 *
1+
#336
0+
#337
0(
b00000000000000000000000000000000 *
1+
#338
0+
#339
b00000000000000000000000000000001 *
1+
#340
0+
#341
b00000000000000000000000000000010 *
1+
#342
0+
#343
1(
b00000000000000000000000000000011 *
1+
#344
0+
#345
0(
b00000000000000000000000000000000 *
1+
#346
0+
#347
b00000000000000000000000000000001 *
1+
#348
0+
#349
b00000000000000000000000000000010 *
1+
#350
0+
#351
1(
b00000000000000000000000000000011 *
1+
#352
0+
#353
0(
b00000000000000000000000000000000 *
1+
#354
0+
#355
b00000000000000000000000000000001 *
1+
#356
0+
#357
b00000000000000000000000000000010 *
1+
#358
0+
#359
1(
b00000000000000000000000000000011 *
1+
#360
0+
#361
0(
b00000000000000000000000000000000 *
1+
#362
0+
#363
b00000000000000000000000000000001 *
1+
#364
0+
#365
b00000000000000000000000000000010 *
1+
#366
0+
#367
1(
b00000000000000000000000000000011 *
1+
#368
0+
#369
0(
b00000000000000000000000000000000 *
1+
#370
0+
#371
b00000000000000000000000000000001 *
1+
#372
0+
#373
b00000000000000000000000000000010 *
1+
#374
0+
#375
1(
b00000000000000000000000000000011 *
1+
#376
0+
#377
0(
b00000000000000000000000000000000 *
1+
#378
0+
#379
b00000000000000000000000000000001 *
1+
#380
0+
#381
b00000000000000000000000000000010 *
1+
#382
0+
#383
1(
b00000000000000000000000000000011 *
1+
#384
0+
#385
0(
b00000000000000000000000000000000 *
1+
#386
0+
#387
b00000000000000000000000000000001 *
1+
#388
0+
#389
b00000000000000000000000000000010 *
1+
#390
0+
#391
1(
b00000000000000000000000000000011 *
1+
#392
0+
#393
0(
b00000000000000000000000000000000 *
1+
#394
0+
#395
b00000000000000000000000000000001 *
1+
#396
0+
#397
b00000000000000000000000000000010 *
1+
#398
0+
#399
1(
b00000000000000000000000000000011 *
1+
#400
0+
#401
0(
b00000000000000000000000000000000 *
1+
#402
0+
#403
b00000000000000000000000000000001 *
1+
#404
0+
#405
b00000000000000000000000000000010 *
1+
#406
0+
#407
1(
b00000000000000000000000000000011 *
1+
#408
0+
#409
0(
b00000000000000000000000000000000 *
1+
#410
0+
#411
b00000000000000000000000000000001 *
1+
#412
0+
#413
b00000000000000000000000000000010 *
1+
#414
0+
#415
1(
b00000000000000000000000000000011 *
1+
#416
0+
#417
0(
b00000000000000000000000000000000 *
1+
#418
0+
#419
b00000000000000000000000000000001 *
1+
#420
0+
#421
b00000000000000000000000000000010 *
1+
#422
0+
#423
1(
b00000000000000000000000000000011 *
1+
#424
0+
#425
0(
b00000000000000000000000000000000 *
1+
#426
0+
#427
b00000000000000000000000000000001 *
1+
#428
0+
#429
b00000000000000000000000000000010 *
1+
#430
0+
#431
1(
b00000000000000000000000000000011 *
1+
#432
0+
#433
0(
b00000000000000000000000000000000 *
1+
#434
0+
#435
b00000000000000000000000000000001 *
1+
#436
0+
#437
b00000000000000000000000000000010 *
1+
#438
0+
#439
1(
b00000000000000000000000000000011 *
1+
#440
0+
#441
0(
b00000000000000000000000000000000 *
1+
#442
0+
#443
b00000000000000000000000000000001 *
1+
#444
0+
#445
b00000000000000000000000000000010 *
1+
#446
0+
#447
1(
b00000000000000000000000000000011 *
1+
#448
0+
#449
0(
b00000000000000000000000000000000 *
1+
#450
0+
#451
b00000000000000000000000000000001 *
1+
#452
0+
#453
b00000000000000000000000000000010 *
1+
#454
0+
#455
1(
b00000000000000000000000000000011 *
1+
#456
0+
#457
0(
b00000000000000000000000000000000 *
1+
#458
0+
#459
b00000000000000000000000000000001 *
1+
#460
0+
#461
b00000000000000000000000000000010 *
1+
#462
0+
#463
1(
b00000000000000000000000000000011 *
1+
#464
0+
#465
0(
b00000000000000000000000000000000 *
1+
#466
0+
#467
b00000000000000000000000000000001 *
1+
#468
0+
#469
b00000000000000000000000000000010 *
1+
#470
0+
#471
1(
b00000000000000000000000000000011 *
1+
#472
0+
#473
0(
b00000000000000000000000000000000 *
1+
#474
0+
#475
b00000000000000000000000000000001 *
1+
#476
0+
#477
b00000000000000000000000000000010 *
1+
#478
0+
#479
1(
b00000000000000000000000000000011 *
1+
#480
0+
#481
0(
b00000000000000000000000000000000 *
1+
#482
0+
#483
b00000000000000000000000000000001 *
1+
#484
0+
#485
b00000000000000000000000000000010 *
1+
#486
0+
#487
1(
b00000000000000000000000000000011 *
1+
#488
0+
#489
0(
b00000000000000000000000000000000 *
1+
#490
0+
#491
b00000000000000000000000000000001 *
1+
#492
0+
#493
b00000000000000000000000000000010 *
1+
#494
0+
#495
1(
b00000000000000000000000000000011 *
1+
#496
0+
#497
0(
b00000000000000000000000000000000 *
1+
#498
0+
#499
b00000000000000000000000000000001 *
1+
#500
0+
#501
b00000000000000000000000000000010 *
1+
#502
0+
#503
1(
b00000000000000000000000000000011 *
1+
#504
0+
#505
0(
b00000000000000000000000000000000 *
1+
#506
0+
#507
b00000000000000000000000000000001 *
1+
#508
0+
#509
b00000000000000000000000000000010 *
1+
#510
0+
#511
1(
b00000000000000000000000000000011 *
1+
#512
0+
#513
0(
b00000000000000000000000000000000 *
1+
#514
0+
#515
b00000000000000000000000000000001 *
1+
#516
0+
#517
b00000000000000000000000000000010 *
1+
#518
0+
#519
1(
b00000000000000000000000000000011 *
1+
#520
0+
#521
0(
b00000000000000000000000000000000 *
1+
#522
0+
#523
b00000000000000000000000000000001 *
1+
#524
0+
#525
b00000000000000000000000000000010 *
1+
#526
0+
#527
1(
b00000000000000000000000000000011 *
1+
#528
0+
#529
0(
b00000000000000000000000000000000 *
1+
#530
0+
#531
b00000000000000000000000000000001 *
1+
#532
0+
#533
b00000000000000000000000000000010 *
1+
#534
0+
#535
1(
b00000000000000000000000000000011 *
1+
#536
0+
#537
0(
b00000000000000000000000000000000 *
1+
#538
0+
#539
b00000000000000000000000000000001 *
1+
#540
0+
#541
b00000000000000000000000000000010 *
1+
#542
0+
#543
1(
b00000000000000000000000000000011 *
1+
#544
0+
#545
0(
b00000000000000000000000000000000 *
1+
#546
0+
#547
b00000000000000000000000000000001 *
1+
#548
0+
#549
b00000000000000000000000000000010 *
1+
#550
0+
#551
1(
b00000000000000000000000000000011 *
1+
#552
0+
#553
0(
b00000000000000000000000000000000 *
1+
#554
0+
#555
b00000000000000000000000000000001 *
1+
#556
0+
#557
b00000000000000000000000000000010 *
1+
#558
0+
#559
1(
b00000000000000000000000000000011 *
1+
#560
0+
#561
0(
b00000000000000000000000000000000 *
1+
#562
0+
#563
b00000000000000000000000000000001 *
1+
#564
0+
#565
b00000000000000000000000000000010 *
1+
#566
0+
#567
1(
b00000000000000000000000000000011 *
1+
#568
0+
#569
0(
b00000000000000000000000000000000 *
1+
#570
0+
#571
b00000000000000000000000000000001 *
1+
#572
0+
#573
b00000000000000000000000000000010 *
1+
#574
0+
#575
1(
b00000000000000000000000000000011 *
1+
#576
0+
#577
0(
b00000000000000000000000000000000 *
1+
#578
0+
#579
b00000000000000000000000000000001 *
1+
#580
0+
#581
b00000000000000000000000000000010 *
1+
#582
0+
#583
1(
b00000000000000000000000000000011 *
1+
#584
0+
#585
0(
b00000000000000000000000000000000 *
1+
#586
0+
#587
b00000000000000000000000000000001 *
1+
#588
0+
#589
b00000000000000000000000000000010 *
1+
#590
0+
#591
1(
b00000000000000000000000000000011 *
1+
#592
0+
#593
0(
b00000000000000000000000000000000 *
1+
#594
0+
#595
b00000000000000000000000000000001 *
1+
#596
0+
#597
b00000000000000000000000000000010 *
1+
#598
0+
#599
1(
b00000000000000000000000000000011 *
1+
#600
0+
#601
0(
b00000000000000000000000000000000 *
1+
#602
0+
#603
b00000000000000000000000000000001 *
1+
#604
0+
#605
b00000000000000000000000000000010 *
1+
#606
0+
#607
1(
b00000000000000000000000000000011 *
1+
#608
0+
#609
0(
b00000000000000000000000000000000 *
1+
#610
0+
#611
b00000000000000000000000000000001 *
1+
#612
0+
#613
b00000000000000000000000000000010 *
1+
#614
0+
#615
1(
b00000000000000000000000000000011 *
1+
#616
0+
#617
0(
b00000000000000000000000000000000 *
1+
#618
0+
#619
b00000000000000000000000000000001 *
1+
#620
0+
#621
b00000000000000000000000000000010 *
1+
#622
0+
#623
1(
b00000000000000000000000000000011 *
1+
#624
0+
#625
0(
b00000000000000000000000000000000 *
1+
#626
0+
#627
b00000000000000000000000000000001 *
1+
#628
0+
#629
b00000000000000000000000000000010 *
1+
#630
0+
#631
1(
b00000000000000000000000000000011 *
1+
#632
0+
#633
0(
b00000000000000000000000000000000 *
1+
#634
0+
#635
b00000000000000000000000000000001 *
1+
#636
0+
#637
b00000000000000000000000000000010 *
1+
#638
0+
#639
1(
b00000000000000000000000000000011 *
1+
#640
0+
#641
0(
b00000000000000000000000000000000 *
1+
#642
0+
#643
b00000000000000000000000000000001 *
1+
#644
0+
#645
b00000000000000000000000000000010 *
1+
#646
0+
#647
1(
b00000000000000000000000000000011 *
1+
#648
0+
#649
0(
b00000000000000000000000000000000 *
1+
#650
0+
#651
b00000000000000000000000000000001 *
1+
#652
0+
#653
b00000000000000000000000000000010 *
1+
#654
0+
#655
1(
b00000000000000000000000000000011 *
1+
#656
0+
#657
0(
b00000000000000000000000000000000 *
1+
#658
0+
#659
b00000000000000000000000000000001 *
1+
#660
0+
#661
b00000000000000000000000000000010 *
1+
#662
0+
#663
1(
b00000000000000000000000000000011 *
1+
#664
0+
#665
0(
b00000000000000000000000000000000 *
1+
#666
0+
#667
b00000000000000000000000000000001 *
1+
#668
0+
#669
b00000000000000000000000000000010 *
1+
#670
0+
#671
1(
b00000000000000000000000000000011 *
1+
#672
0+
#673
0(
b00000000000000000000000000000000 *
1+
#674
0+
#675
b00000000000000000000000000000001 *
1+
#676
0+
#677
b00000000000000000000000000000010 *
1+
#678
0+
#679
1(
b00000000000000000000000000000011 *
1+
#680
0+
#681
0(
b00000000000000000000000000000000 *
1+
#682
0+
#683
b00000000000000000000000000000001 *
1+
#684
0+
#685
b00000000000000000000000000000010 *
1+
#686
0+
#687
1(
b00000000000000000000000000000011 *
1+
#688
0+
#689
0(
b00000000000000000000000000000000 *
1+
#690
0+
#691
b00000000000000000000000000000001 *
1+
#692
0+
#693
b00000000000000000000000000000010 *
1+
#694
0+
#695
1(
b00000000000000000000000000000011 *
1+
#696
0+
#697
0(
b00000000000000000000000000000000 *
1+
#698
0+
#699
b00000000000000000000000000000001 *
1+
#700
0+
#701
b00000000000000000000000000000010 *
1+
#702
0+
#703
1(
b00000000000000000000000000000011 *
1+
#704
0+
#705
0(
b00000000000000000000000000000000 *
1+
#706
0+
#707
b00000000000000000000000000000001 *
1+
#708
0+
#709
b00000000000000000000000000000010 *
1+
#710
0+
#711
1(
b00000000000000000000000000000011 *
1+
#712
0+
#713
0(
b00000000000000000000000000000000 *
1+
#714
0+
#715
b00000000000000000000000000000001 *
1+
#716
0+
#717
b00000000000000000000000000000010 *
1+
#718
0+
#719
1(
b00000000000000000000000000000011 *
1+
#720
0+
#721
0(
b00000000000000000000000000000000 *
1+
#722
0+
#723
b00000000000000000000000000000001 *
1+
#724
0+
#725
b00000000000000000000000000000010 *
1+
#726
0+
#727
1(
b00000000000000000000000000000011 *
1+
#728
0+
#729
0(
b00000000000000000000000000000000 *
1+
#730
0+
#731
b00000000000000000000000000000001 *
1+
#732
0+
#733
b00000000000000000000000000000010 *
1+
#734
0+
#735
1(
b00000000000000000000000000000011 *
1+
#736
0+
#737
0(
b00000000000000000000000000000000 *
1+
#738
0+
#739
b00000000000000000000000000000001 *
1+
#740
0+
#741
b00000000000000000000000000000010 *
1+
#742
0+
#743
1(
b00000000000000000000000000000011 *
1+
#744
0+
#745
0(
b00000000000000000000000000000000 *
1+
#746
0+
#747
b00000000000000000000000000000001 *
1+
#748
0+
#749
b00000000000000000000000000000010 *
1+
#750
0+
#751
1(
b00000000000000000000000000000011 *
1+
#752
0+
#753
0(
b00000000000000000000000000000000 *
1+
#754
0+
#755
b00000000000000000000000000000001 *
1+
#756
0+
#757
b00000000000000000000000000000010 *
1+
#758
0+
#759
1(
b00000000000000000000000000000011 *
1+
#760
0+
#761
0(
b00000000000000000000000000000000 *
1+
#762
0+
#763
b00000000000000000000000000000001 *
1+
#764
0+
#765
b00000000000000000000000000000010 *
1+
#766
0+
#767
1(
b00000000000000000000000000000011 *
1+
#768
0+
#769
0(
b00000000000000000000000000000000 *
1+
#770
0+
#771
b00000000000000000000000000000001 *
1+
#772
0+
#773
b00000000000000000000000000000010 *
1+
#774
0+
#775
1(
b00000000000000000000000000000011 *
1+
#776
0+
#777
0(
b00000000000000000000000000000000 *
1+
#778
0+
#779
b00000000000000000000000000000001 *
1+
#780
0+
#781
b00000000000000000000000000000010 *
1+
#782
0+
#783
1(
b00000000000000000000000000000011 *
1+
#784
0+
#785
0(
b00000000000000000000000000000000 *
1+
#786
0+
#787
b00000000000000000000000000000001 *
1+
#788
0+
#789
b00000000000000000000000000000010 *
1+
#790
0+
#791
1(
b00000000000000000000000000000011 *
1+
#792
0+
#793
0(
b00000000000000000000000000000000 *
1+
#794
0+
#795
b00000000000000000000000000000001 *
1+
#796
0+
#797
b00000000000000000000000000000010 *
1+
#798
0+
#799
1(
b00000000000000000000000000000011 *
1+
#800
0+
#801
0(
b00000000000000000000000000000000 *
1+
#802
0+
#803
b00000000000000000000000000000001 *
1+
#804
0+
#805
b00000000000000000000000000000010 *
1+
#806
0+
#807
1(
b00000000000000000000000000000011 *
1+
#808
0+
#809
0(
b00000000000000000000000000000000 *
1+
#810
0+
#811
b00000000000000000000000000000001 *
1+
#812
0+
#813
b00000000000000000000000000000010 *
1+
#814
0+
#815
1(
b00000000000000000000000000000011 *
1+
#816
0+
#817
0(
b00000000000000000000000000000000 *
1+
#818
0+
#819
b00000000000000000000000000000001 *
1+
#820
0+
#821
b00000000000000000000000000000010 *
1+
#822
0+
#823
1(
b00000000000000000000000000000011 *
1+
#824
0+
#825
0(
b00000000000000000000000000000000 *
1+
#826
0+
#827
b00000000000000000000000000000001 *
1+
#828
0+
#829
b00000000000000000000000000000010 *
1+
#830
0+
#831
1(
b00000000000000000000000000000011 *
1+
#832
0+
#833
0(
b00000000000000000000000000000000 *
1+
#834
0+
#835
b00000000000000000000000000000001 *
1+
#836
0+
#837
b00000000000000000000000000000010 *
1+
#838
0+
#839
1(
b00000000000000000000000000000011 *
1+
#840
0+
#841
0(
b00000000000000000000000000000000 *
1+
#842
0+
#843
b00000000000000000000000000000001 *
1+
#844
0+
#845
b00000000000000000000000000000010 *
1+
#846
0+
#847
1(
b00000000000000000000000000000011 *
1+
#848
0+
#849
0(
b00000000000000000000000000000000 *
1+
#850
0+
#851
b00000000000000000000000000000001 *
1+
#852
0+
#853
b00000000000000000000000000000010 *
1+
#854
0+
#855
1(
b00000000000000000000000000000011 *
1+
#856
0+
#857
0(
b00000000000000000000000000000000 *
1+
#858
0+
#859
b00000000000000000000000000000001 *
1+
#860
0+
#861
b00000000000000000000000000000010 *
1+
#862
0+
#863
1(
b00000000000000000000000000000011 *
1+
#864
0+
#865
0(
b00000000000000000000000000000000 *
1+
#866
0+
#867
b00000000000000000000000000000001 *
1+
#868
0+
#869
b00000000000000000000000000000010 *
1+
#870
0+
#871
1(
b00000000000000000000000000000011 *
1+
#872
0+
#873
0(
b00000000000000000000000000000000 *
1+
#874
0+
#875
b00000000000000000000000000000001 *
1+
#876
0+
#877
b00000000000000000000000000000010 *
1+
#878
0+
#879
1(
b00000000000000000000000000000011 *
1+
#880
0+
#881
0(
b00000000000000000000000000000000 *
1+
#882
0+
#883
b00000000000000000000000000000001 *
1+
#884
0+
#885
b00000000000000000000000000000010 *
1+
#886
0+
#887
1(
b00000000000000000000000000000011 *
1+
#888
0+
#889
0(
b00000000000000000000000000000000 *
1+
#890
0+
#891
b00000000000000000000000000000001 *
1+
#892
0+
#893
b00000000000000000000000000000010 *
1+
#894
0+
#895
1(
b00000000000000000000000000000011 *
1+
#896
0+
#897
0(
b00000000000000000000000000000000 *
1+
#898
0+
#899
b00000000000000000000000000000001 *
1+
#900
0+
#901
b00000000000000000000000000000010 *
1+
#902
0+
#903
1(
b00000000000000000000000000000011 *
1+
#904
0+
#905
0(
b00000000000000000000000000000000 *
1+
