standalone_subprojects/communication_protocols/spi/modules/spi_slave.v
module spi_slave #(
    parameter int WIDTH = 15
) (
    input load,
    output wire miso,
    input sclk,
    input mosi,
    input clr,
    output reg [WIDTH-1:0] sr_stx,
    output reg [WIDTH-1:0] sr_srx = 0,
    output reg [WIDTH-1:0] dout = 0,
    input [WIDTH-1:0] din
);
  assign miso = sr_stx[WIDTH-1];

  always @(posedge load) begin
    dout <= sr_srx;
  end

  always @(posedge sclk) begin
    sr_srx <= sr_srx << 1 | mosi;
  end

  always @(negedge sclk or posedge load) begin
    if (load) sr_stx <= din;
    else if (clr) sr_stx <= 0;
    else sr_stx <= sr_stx << 1;
  end
endmodule

standalone_subprojects/communication_protocols/spi/modules/spi_master.v
module spi_master #(
    parameter int CLKFREQ = 27000000,  // 27MHz
    parameter int WIDTH = 15,
    parameter int SPIFREQ = 250000  // 250KHz => 4us
) (
    input st,
    input clk,

    output reg sclk = 0,
    output reg load = 1,
    output wire mosi,
    input miso,

    input [WIDTH-1:0] din,
    output reg [WIDTH-1:0] dout = 0,
    input clr,
    output reg [WIDTH-1:0] sr_mtx = 0,
    output reg [WIDTH-1:0] sr_mrx = 0,
    output reg [7:0] cb_bit = 0,
    output wire ce,
    output wire ce_tact
);
  localparam int NT = CLKFREQ / (2 * SPIFREQ);

  reg [31:0] cb_tact = 0;

  assign ce = (cb_tact == NT - 1);
  assign mosi = sr_mtx[WIDTH-1];
  assign ce_tact = ce & sclk;

  wire start = st & load;

  always @(posedge clk) begin
    load <= st ? 0 : ((cb_bit == WIDTH - 1) & ce_tact) ? 1 : load;
    cb_tact <= (start | ce) ? 0 : cb_tact + 1;
    sclk <= load ? 0 : ce ? !sclk : sclk;
    sr_mtx <= start ? din : ce_tact ? sr_mtx << 1 : sr_mtx;
    cb_bit <= start ? 0 : ce_tact ? cb_bit + 1 : cb_bit;
  end

  always @(posedge sclk) begin
    sr_mrx <= sr_mrx << 1 | miso;
  end

  always @(posedge load) begin
    dout <= sr_mrx;
  end
endmodule

standalone_subprojects/communication_protocols/spi/modules/spi_test_slave.v
module spi_test_slave #(
    parameter int WIDTH   = 15,
    parameter int CLKFREQ = 8,
    parameter int SPIFREQ = 2

) (
    output wire load,
    output wire sclk,
    output wire miso,
    output wire mosi,

    input st,
    input clk,
    input rst,

    input [WIDTH-1:0] mtx_dat,
    output wire [WIDTH-1:0] mrx_dat,
    output wire [WIDTH-1:0] sr_mtx,
    output wire [WIDTH-1:0] sr_mrx,
    output wire [7:0] cb_bit,
    output wire ce_tact,

    input [WIDTH-1:0] stx_dat,
    output wire [WIDTH-1:0] sr_stx,
    output wire [WIDTH-1:0] sr_srx,
    output wire [WIDTH-1:0] srx_dat
);

  wire test_ce;

  spi_master #(
      .WIDTH  (WIDTH),
      .CLKFREQ(CLKFREQ),
      .SPIFREQ(SPIFREQ)
  ) master (
      .clk(clk),
      .st(st),
      .din(mtx_dat),
      .dout(mrx_dat),
      .load(load),
      .sclk(sclk),
      .mosi(mosi),
      .clr(rst),
      .miso(miso),
      .sr_mtx(sr_mtx),
      .sr_mrx(sr_mrx),
      .cb_bit(cb_bit),
      .ce_tact(ce_tact),
      .ce(test_ce)
  );

  spi_slave #(
      .WIDTH(WIDTH)
  ) slave (
      .din(stx_dat),
      .dout(srx_dat),
      .load(load),
      .miso(miso),
      .sclk(sclk),
      .mosi(mosi),
      .sr_stx(sr_stx),
      .sr_srx(sr_srx),
      .clr(rst)
  );
endmodule

standalone_subprojects/communication_protocols/spi/testbenches/spi_both_tb.v
module spi_both_tb;
  localparam int WIDTH = 15;

  reg clk;
  reg st;
  reg load;
  reg [WIDTH-1:0] mtx_dat;
  reg [WIDTH-1:0] stx_dat;
  reg rst;

  wire mosi;
  wire miso;
  wire sclk;

  initial begin
    $dumpfile("spi_both_tb.vcd");
    $dumpvars(0, spi_both_tb);

    st = 0;
    rst = 0;
    stx_dat = 0;
    mtx_dat = 0;
    #26;

    st = 1;
    #2;

    mtx_dat = 15'b101110010100011;
    stx_dat = 15'b101011010101010;
    st = 0;
    #128;

    st = 1;
    #2;
    st = 0;

    #128;

    st  = 1;
    rst = 0;

    #2;

    st = 0;

    #128;

    $finish;
  end

  always begin
    clk = 1;
    #1;
    clk = 0;
    #1;
  end

  spi_test_slave #(
      .WIDTH  (WIDTH),
      .CLKFREQ(8),
      .SPIFREQ(2)
  ) master (
      .st(st),
      .clk(clk),
      .rst(rst),
      .mtx_dat(mtx_dat),
      .stx_dat(stx_dat),
      .mosi(mosi),
      .miso(miso),
      .sclk(sclk),
      .load(load)
  );
endmodule

standalone_subprojects/communication_protocols/spi/spi_both_tb.vcd
$version Generated by VerilatedVcd $end
$timescale 1ps $end
 $scope module $rootio $end
 $upscope $end
 $scope module spi_both_tb $end
  $var wire 32 7 WIDTH [31:0] $end
  $var wire 1 + clk $end
  $var wire 1 , st $end
  $var wire 1 # load $end
  $var wire 15 - mtx_dat [14:0] $end
  $var wire 15 . stx_dat [14:0] $end
  $var wire 1 / rst $end
  $var wire 1 $ mosi $end
  $var wire 1 0 miso $end
  $var wire 1 % sclk $end
  $scope module master $end
   $var wire 32 7 WIDTH [31:0] $end
   $var wire 32 8 CLKFREQ [31:0] $end
   $var wire 32 9 SPIFREQ [31:0] $end
   $var wire 1 # load $end
   $var wire 1 % sclk $end
   $var wire 1 0 miso $end
   $var wire 1 $ mosi $end
   $var wire 1 , st $end
   $var wire 1 + clk $end
   $var wire 1 / rst $end
   $var wire 15 - mtx_dat [14:0] $end
   $var wire 15 1 mrx_dat [14:0] $end
   $var wire 15 & sr_mtx [14:0] $end
   $var wire 15 2 sr_mrx [14:0] $end
   $var wire 8 ' cb_bit [7:0] $end
   $var wire 1 ( ce_tact $end
   $var wire 15 . stx_dat [14:0] $end
   $var wire 15 3 sr_stx [14:0] $end
   $var wire 15 4 sr_srx [14:0] $end
   $var wire 15 5 srx_dat [14:0] $end
   $var wire 1 ) test_ce $end
   $scope module master $end
    $var wire 32 8 CLKFREQ [31:0] $end
    $var wire 32 7 WIDTH [31:0] $end
    $var wire 32 9 SPIFREQ [31:0] $end
    $var wire 1 , st $end
    $var wire 1 + clk $end
    $var wire 1 % sclk $end
    $var wire 1 # load $end
    $var wire 1 $ mosi $end
    $var wire 1 0 miso $end
    $var wire 15 - din [14:0] $end
    $var wire 15 1 dout [14:0] $end
    $var wire 1 / clr $end
    $var wire 15 & sr_mtx [14:0] $end
    $var wire 15 2 sr_mrx [14:0] $end
    $var wire 8 ' cb_bit [7:0] $end
    $var wire 1 ) ce $end
    $var wire 1 ( ce_tact $end
    $var wire 32 9 NT [31:0] $end
    $var wire 32 * cb_tact [31:0] $end
    $var wire 1 6 start $end
   $upscope $end
   $scope module slave $end
    $var wire 32 7 WIDTH [31:0] $end
    $var wire 1 # load $end
    $var wire 1 0 miso $end
    $var wire 1 % sclk $end
    $var wire 1 $ mosi $end
    $var wire 1 / clr $end
    $var wire 15 3 sr_stx [14:0] $end
    $var wire 15 4 sr_srx [14:0] $end
    $var wire 15 5 dout [14:0] $end
    $var wire 15 . din [14:0] $end
   $upscope $end
  $upscope $end
 $upscope $end
$enddefinitions $end


#0
1#
0$
0%
b000000000000000 &
b00000000 '
0(
0)
b00000000000000000000000000000000 *
1+
0,
b000000000000000 -
b000000000000000 .
0/
00
b000000000000000 1
b000000000000000 2
b000000000000000 3
b000000000000000 4
b000000000000000 5
06
b00000000000000000000000000001111 7
b00000000000000000000000000001000 8
b00000000000000000000000000000010 9
#1
0+
#2
1)
b00000000000000000000000000000001 *
1+
#3
0+
#4
0)
b00000000000000000000000000000000 *
1+
#5
0+
#6
1)
b00000000000000000000000000000001 *
1+
#7
0+
#8
0)
b00000000000000000000000000000000 *
1+
#9
0+
#10
1)
b00000000000000000000000000000001 *
1+
#11
0+
#12
0)
b00000000000000000000000000000000 *
1+
#13
0+
#14
1)
b00000000000000000000000000000001 *
1+
#15
0+
#16
0)
b00000000000000000000000000000000 *
1+
#17
0+
#18
1)
b00000000000000000000000000000001 *
1+
#19
0+
#20
0)
b00000000000000000000000000000000 *
1+
#21
0+
#22
1)
b00000000000000000000000000000001 *
1+
#23
0+
#24
0)
b00000000000000000000000000000000 *
1+
#25
0+
#26
0#
1+
1,
#27
0+
#28
1)
b00000000000000000000000000000001 *
1+
0,
b101110010100011 -
b101011010101010 .
#29
0+
#30
1%
0)
b00000000000000000000000000000000 *
1+
#31
0+
#32
1(
1)
b00000000000000000000000000000001 *
1+
#33
0+
#34
0%
b00000001 '
0(
0)
b00000000000000000000000000000000 *
1+
#35
0+
#36
1)
b00000000000000000000000000000001 *
1+
#37
0+
#38
1%
0)
b00000000000000000000000000000000 *
1+
#39
0+
#40
1(
1)
b00000000000000000000000000000001 *
1+
#41
0+
#42
0%
b00000010 '
0(
0)
b00000000000000000000000000000000 *
1+
#43
0+
#44
1)
b00000000000000000000000000000001 *
1+
#45
0+
#46
1%
0)
b00000000000000000000000000000000 *
1+
#47
0+
#48
1(
1)
b00000000000000000000000000000001 *
1+
#49
0+
#50
0%
b00000011 '
0(
0)
b00000000000000000000000000000000 *
1+
#51
0+
#52
1)
b00000000000000000000000000000001 *
1+
#53
0+
#54
1%
0)
b00000000000000000000000000000000 *
1+
#55
0+
#56
1(
1)
b00000000000000000000000000000001 *
1+
#57
0+
#58
0%
b00000100 '
0(
0)
b00000000000000000000000000000000 *
1+
#59
0+
#60
1)
b00000000000000000000000000000001 *
1+
#61
0+
#62
1%
0)
b00000000000000000000000000000000 *
1+
#63
0+
#64
1(
1)
b00000000000000000000000000000001 *
1+
#65
0+
#66
0%
b00000101 '
0(
0)
b00000000000000000000000000000000 *
1+
#67
0+
#68
1)
b00000000000000000000000000000001 *
1+
#69
0+
#70
1%
0)
b00000000000000000000000000000000 *
1+
#71
0+
#72
1(
1)
b00000000000000000000000000000001 *
1+
#73
0+
#74
0%
b00000110 '
0(
0)
b00000000000000000000000000000000 *
1+
#75
0+
#76
1)
b00000000000000000000000000000001 *
1+
#77
0+
#78
1%
0)
b00000000000000000000000000000000 *
1+
#79
0+
#80
1(
1)
b00000000000000000000000000000001 *
1+
#81
0+
#82
0%
b00000111 '
0(
0)
b00000000000000000000000000000000 *
1+
#83
0+
#84
1)
b00000000000000000000000000000001 *
1+
#85
0+
#86
1%
0)
b00000000000000000000000000000000 *
1+
#87
0+
#88
1(
1)
b00000000000000000000000000000001 *
1+
#89
0+
#90
0%
b00001000 '
0(
0)
b00000000000000000000000000000000 *
1+
#91
0+
#92
1)
b00000000000000000000000000000001 *
1+
#93
0+
#94
1%
0)
b00000000000000000000000000000000 *
1+
#95
0+
#96
1(
1)
b00000000000000000000000000000001 *
1+
#97
0+
#98
0%
b00001001 '
0(
0)
b00000000000000000000000000000000 *
1+
#99
0+
#100
1)
b00000000000000000000000000000001 *
1+
#101
0+
#102
1%
0)
b00000000000000000000000000000000 *
1+
#103
0+
#104
1(
1)
b00000000000000000000000000000001 *
1+
#105
0+
#106
0%
b00001010 '
0(
0)
b00000000000000000000000000000000 *
1+
#107
0+
#108
1)
b00000000000000000000000000000001 *
1+
#109
0+
#110
1%
0)
b00000000000000000000000000000000 *
1+
#111
0+
#112
1(
1)
b00000000000000000000000000000001 *
1+
#113
0+
#114
0%
b00001011 '
0(
0)
b00000000000000000000000000000000 *
1+
#115
0+
#116
1)
b00000000000000000000000000000001 *
1+
#117
0+
#118
1%
0)
b00000000000000000000000000000000 *
1+
#119
0+
#120
1(
1)
b00000000000000000000000000000001 *
1+
#121
0+
#122
0%
b00001100 '
0(
0)
b00000000000000000000000000000000 *
1+
#123
0+
#124
1)
b00000000000000000000000000000001 *
1+
#125
0+
#126
1%
0)
b00000000000000000000000000000000 *
1+
#127
0+
#128
1(
1)
b00000000000000000000000000000001 *
1+
#129
0+
#130
0%
b00001101 '
0(
0)
b00000000000000000000000000000000 *
1+
#131
0+
#132
1)
b00000000000000000000000000000001 *
1+
#133
0+
#134
1%
0)
b00000000000000000000000000000000 *
1+
#135
0+
#136
1(
1)
b00000000000000000000000000000001 *
1+
#137
0+
#138
0%
b00001110 '
0(
0)
b00000000000000000000000000000000 *
1+
#139
0+
#140
1)
b00000000000000000000000000000001 *
1+
#141
0+
#142
1%
0)
b00000000000000000000000000000000 *
1+
#143
0+
#144
1(
1)
b00000000000000000000000000000001 *
1+
#145
0+
#146
1#
0%
b00001111 '
0(
0)
b00000000000000000000000000000000 *
1+
10
b101011010101010 3
#147
0+
#148
1)
b00000000000000000000000000000001 *
1+
#149
0+
#150
0)
b00000000000000000000000000000000 *
1+
#151
0+
#152
1)
b00000000000000000000000000000001 *
1+
#153
0+
#154
0)
b00000000000000000000000000000000 *
1+
#155
0+
#156
0#
1$
b101110010100011 &
b00000000 '
1+
1,
#157
0+
#158
1)
b00000000000000000000000000000001 *
1+
0,
#159
0+
#160
1%
0)
b00000000000000000000000000000000 *
1+
b000000000000001 2
b000000000000001 4
#161
0+
#162
1(
1)
b00000000000000000000000000000001 *
1+
#163
0+
#164
0$
0%
b011100101000110 &
b00000001 '
0(
0)
b00000000000000000000000000000000 *
1+
00
b010110101010100 3
#165
0+
#166
1)
b00000000000000000000000000000001 *
1+
#167
0+
#168
1%
0)
b00000000000000000000000000000000 *
1+
b000000000000010 2
b000000000000010 4
#169
0+
#170
1(
1)
b00000000000000000000000000000001 *
1+
#171
0+
#172
1$
0%
b111001010001100 &
b00000010 '
0(
0)
b00000000000000000000000000000000 *
1+
10
b101101010101000 3
#173
0+
#174
1)
b00000000000000000000000000000001 *
1+
#175
0+
#176
1%
0)
b00000000000000000000000000000000 *
1+
b000000000000101 2
b000000000000101 4
#177
0+
#178
1(
1)
b00000000000000000000000000000001 *
1+
#179
0+
#180
0%
b110010100011000 &
b00000011 '
0(
0)
b00000000000000000000000000000000 *
1+
00
b011010101010000 3
#181
0+
#182
1)
b00000000000000000000000000000001 *
1+
#183
0+
#184
1%
0)
b00000000000000000000000000000000 *
1+
b000000000001010 2
b000000000001011 4
#185
0+
#186
1(
1)
b00000000000000000000000000000001 *
1+
#187
0+
#188
0%
b100101000110000 &
b00000100 '
0(
0)
b00000000000000000000000000000000 *
1+
10
b110101010100000 3
#189
0+
#190
1)
b00000000000000000000000000000001 *
1+
#191
0+
#192
1%
0)
b00000000000000000000000000000000 *
1+
b000000000010101 2
b000000000010111 4
#193
0+
#194
1(
1)
b00000000000000000000000000000001 *
1+
#195
0+
#196
0$
0%
b001010001100000 &
b00000101 '
0(
0)
b00000000000000000000000000000000 *
1+
b101010101000000 3
#197
0+
#198
1)
b00000000000000000000000000000001 *
1+
#199
0+
#200
1%
0)
b00000000000000000000000000000000 *
1+
b000000000101011 2
b000000000101110 4
#201
0+
#202
1(
1)
b00000000000000000000000000000001 *
1+
#203
0+
#204
0%
b010100011000000 &
b00000110 '
0(
0)
b00000000000000000000000000000000 *
1+
00
b010101010000000 3
#205
0+
#206
1)
b00000000000000000000000000000001 *
1+
#207
0+
#208
1%
0)
b00000000000000000000000000000000 *
1+
b000000001010110 2
b000000001011100 4
#209
0+
#210
1(
1)
b00000000000000000000000000000001 *
1+
#211
0+
#212
1$
0%
b101000110000000 &
b00000111 '
0(
0)
b00000000000000000000000000000000 *
1+
10
b101010100000000 3
#213
0+
#214
1)
b00000000000000000000000000000001 *
1+
#215
0+
#216
1%
0)
b00000000000000000000000000000000 *
1+
b000000010101101 2
b000000010111001 4
#217
0+
#218
1(
1)
b00000000000000000000000000000001 *
1+
#219
0+
#220
0$
0%
b010001100000000 &
b00001000 '
0(
0)
b00000000000000000000000000000000 *
1+
00
b010101000000000 3
#221
0+
#222
1)
b00000000000000000000000000000001 *
1+
#223
0+
#224
1%
0)
b00000000000000000000000000000000 *
1+
b000000101011010 2
b000000101110010 4
#225
0+
#226
1(
1)
b00000000000000000000000000000001 *
1+
#227
0+
#228
1$
0%
b100011000000000 &
b00001001 '
0(
0)
b00000000000000000000000000000000 *
1+
10
b101010000000000 3
#229
0+
#230
1)
b00000000000000000000000000000001 *
1+
#231
0+
#232
1%
0)
b00000000000000000000000000000000 *
1+
b000001010110101 2
b000001011100101 4
#233
0+
#234
1(
1)
b00000000000000000000000000000001 *
1+
#235
0+
#236
0$
0%
b000110000000000 &
b00001010 '
0(
0)
b00000000000000000000000000000000 *
1+
00
b010100000000000 3
#237
0+
#238
1)
b00000000000000000000000000000001 *
1+
#239
0+
#240
1%
0)
b00000000000000000000000000000000 *
1+
b000010101101010 2
b000010111001010 4
#241
0+
#242
1(
1)
b00000000000000000000000000000001 *
1+
#243
0+
#244
0%
b001100000000000 &
b00001011 '
0(
0)
b00000000000000000000000000000000 *
1+
10
b101000000000000 3
#245
0+
#246
1)
b00000000000000000000000000000001 *
1+
#247
0+
#248
1%
0)
b00000000000000000000000000000000 *
1+
b000101011010101 2
b000101110010100 4
#249
0+
#250
1(
1)
b00000000000000000000000000000001 *
1+
#251
0+
#252
0%
b011000000000000 &
b00001100 '
0(
0)
b00000000000000000000000000000000 *
1+
00
b010000000000000 3
#253
0+
#254
1)
b00000000000000000000000000000001 *
1+
#255
0+
#256
1%
0)
b00000000000000000000000000000000 *
1+
b001010110101010 2
b001011100101000 4
#257
0+
#258
1(
1)
b00000000000000000000000000000001 *
1+
#259
0+
#260
1$
0%
b110000000000000 &
b00001101 '
0(
0)
b00000000000000000000000000000000 *
1+
10
b100000000000000 3
#261
0+
#262
1)
b00000000000000000000000000000001 *
1+
#263
0+
#264
1%
0)
b00000000000000000000000000000000 *
1+
b010101101010101 2
b010111001010001 4
#265
0+
#266
1(
1)
b00000000000000000000000000000001 *
1+
#267
0+
#268
0%
b100000000000000 &
b00001110 '
0(
0)
b00000000000000000000000000000000 *
1+
00
b000000000000000 3
#269
0+
#270
1)
b00000000000000000000000000000001 *
1+
#271
0+
#272
1%
0)
b00000000000000000000000000000000 *
1+
b101011010101010 2
b101110010100011 4
#273
0+
#274
1(
1)
b00000000000000000000000000000001 *
1+
#275
0+
#276
1#
0$
0%
b000000000000000 &
b00001111 '
0(
0)
b00000000000000000000000000000000 *
1+
10
b101011010101010 1
b101011010101010 3
b101110010100011 5
#277
0+
#278
1)
b00000000000000000000000000000001 *
1+
#279
0+
#280
0)
b00000000000000000000000000000000 *
1+
#281
0+
#282
1)
b00000000000000000000000000000001 *
1+
#283
0+
#284
0)
b00000000000000000000000000000000 *
1+
#285
0+
#286
0#
1$
b101110010100011 &
b00000000 '
1+
1,
#287
0+
#288
1)
b00000000000000000000000000000001 *
1+
0,
#289
0+
#290
1%
0)
b00000000000000000000000000000000 *
1+
b010110101010101 2
b011100101000111 4
#291
0+
#292
1(
1)
b00000000000000000000000000000001 *
1+
#293
0+
#294
0$
0%
b011100101000110 &
b00000001 '
0(
0)
b00000000000000000000000000000000 *
1+
00
b010110101010100 3
#295
0+
#296
1)
b00000000000000000000000000000001 *
1+
#297
0+
#298
1%
0)
b00000000000000000000000000000000 *
1+
b101101010101010 2
b111001010001110 4
#299
0+
#300
1(
1)
b00000000000000000000000000000001 *
1+
#301
0+
#302
1$
0%
b111001010001100 &
b00000010 '
0(
0)
b00000000000000000000000000000000 *
1+
10
b101101010101000 3
#303
0+
#304
1)
b00000000000000000000000000000001 *
1+
#305
0+
#306
1%
0)
b00000000000000000000000000000000 *
1+
b011010101010101 2
b110010100011101 4
#307
0+
#308
1(
1)
b00000000000000000000000000000001 *
1+
#309
0+
#310
0%
b110010100011000 &
b00000011 '
0(
0)
b00000000000000000000000000000000 *
1+
00
b011010101010000 3
#311
0+
#312
1)
b00000000000000000000000000000001 *
1+
#313
0+
#314
1%
0)
b00000000000000000000000000000000 *
1+
b110101010101010 2
b100101000111011 4
#315
0+
#316
1(
1)
b00000000000000000000000000000001 *
1+
#317
0+
#318
0%
b100101000110000 &
b00000100 '
0(
0)
b00000000000000000000000000000000 *
1+
10
b110101010100000 3
#319
0+
#320
1)
b00000000000000000000000000000001 *
1+
#321
0+
#322
1%
0)
b00000000000000000000000000000000 *
1+
b101010101010101 2
b001010001110111 4
#323
0+
#324
1(
1)
b00000000000000000000000000000001 *
1+
#325
0+
#326
0$
0%
b001010001100000 &
b00000101 '
0(
0)
b00000000000000000000000000000000 *
1+
b101010101000000 3
#327
0+
#328
1)
b00000000000000000000000000000001 *
1+
#329
0+
#330
1%
0)
b00000000000000000000000000000000 *
1+
b010101010101011 2
b010100011101110 4
#331
0+
#332
1(
1)
b00000000000000000000000000000001 *
1+
#333
0+
#334
0%
b010100011000000 &
b00000110 '
0(
0)
b00000000000000000000000000000000 *
1+
00
b010101010000000 3
#335
0+
#336
1)
b00000000000000000000000000000001 *
1+
#337
0+
#338
1%
0)
b00000000000000000000000000000000 *
1+
b101010101010110 2
b101000111011100 4
#339
0+
#340
1(
1)
b00000000000000000000000000000001 *
1+
#341
0+
#342
1$
0%
b101000110000000 &
b00000111 '
0(
0)
b00000000000000000000000000000000 *
1+
10
b101010100000000 3
#343
0+
#344
1)
b00000000000000000000000000000001 *
1+
#345
0+
#346
1%
0)
b00000000000000000000000000000000 *
1+
b010101010101101 2
b010001110111001 4
#347
0+
#348
1(
1)
b00000000000000000000000000000001 *
1+
#349
0+
#350
0$
0%
b010001100000000 &
b00001000 '
0(
0)
b00000000000000000000000000000000 *
1+
00
b010101000000000 3
#351
0+
#352
1)
b00000000000000000000000000000001 *
1+
#353
0+
#354
1%
0)
b00000000000000000000000000000000 *
1+
b101010101011010 2
b100011101110010 4
#355
0+
#356
1(
1)
b00000000000000000000000000000001 *
1+
#357
0+
#358
1$
0%
b100011000000000 &
b00001001 '
0(
0)
b00000000000000000000000000000000 *
1+
10
b101010000000000 3
#359
0+
#360
1)
b00000000000000000000000000000001 *
1+
#361
0+
#362
1%
0)
b00000000000000000000000000000000 *
1+
b010101010110101 2
b000111011100101 4
#363
0+
#364
1(
1)
b00000000000000000000000000000001 *
1+
#365
0+
#366
0$
0%
b000110000000000 &
b00001010 '
0(
0)
b00000000000000000000000000000000 *
1+
00
b010100000000000 3
#367
0+
#368
1)
b00000000000000000000000000000001 *
1+
#369
0+
#370
1%
0)
b00000000000000000000000000000000 *
1+
b101010101101010 2
b001110111001010 4
#371
0+
#372
1(
1)
b00000000000000000000000000000001 *
1+
#373
0+
#374
0%
b001100000000000 &
b00001011 '
0(
0)
b00000000000000000000000000000000 *
1+
10
b101000000000000 3
#375
0+
#376
1)
b00000000000000000000000000000001 *
1+
#377
0+
#378
1%
0)
b00000000000000000000000000000000 *
1+
b010101011010101 2
b011101110010100 4
#379
0+
#380
1(
1)
b00000000000000000000000000000001 *
1+
#381
0+
#382
0%
b011000000000000 &
b00001100 '
0(
0)
b00000000000000000000000000000000 *
1+
00
b010000000000000 3
#383
0+
#384
1)
b00000000000000000000000000000001 *
1+
#385
0+
#386
1%
0)
b00000000000000000000000000000000 *
1+
b101010110101010 2
b111011100101000 4
#387
0+
#388
1(
1)
b00000000000000000000000000000001 *
1+
#389
0+
#390
1$
0%
b110000000000000 &
b00001101 '
0(
0)
b00000000000000000000000000000000 *
1+
10
b100000000000000 3
#391
0+
#392
1)
b00000000000000000000000000000001 *
1+
#393
0+
#394
1%
0)
b00000000000000000000000000000000 *
1+
b010101101010101 2
b110111001010001 4
#395
0+
#396
1(
1)
b00000000000000000000000000000001 *
1+
#397
0+
#398
0%
b100000000000000 &
b00001110 '
0(
0)
b00000000000000000000000000000000 *
1+
00
b000000000000000 3
#399
0+
#400
1)
b00000000000000000000000000000001 *
1+
#401
0+
#402
1%
0)
b00000000000000000000000000000000 *
1+
b101011010101010 2
b101110010100011 4
#403
0+
#404
1(
1)
b00000000000000000000000000000001 *
1+
#405
0+
#406
1#
0$
0%
b000000000000000 &
b00001111 '
0(
0)
b00000000000000000000000000000000 *
1+
10
b101011010101010 3
#407
0+
#408
1)
b00000000000000000000000000000001 *
1+
#409
0+
#410
0)
b00000000000000000000000000000000 *
1+
#411
0+
#412
1)
b00000000000000000000000000000001 *
1+
#413
0+
#414
0)
b00000000000000000000000000000000 *
1+
#415
0+
#416
1)
b00000000000000000000000000000001 *
1+
