src/verilog/counters/VCG4RE/device.v
module VCG4RE ( input clk, output wire tc,
                input ce,  output wire ceo,
                input r,   output wire [3:0]q );

        reg [4:0]sup = 0 ;

        assign tc = (sup[4:0] == ((1 << 4) | 1)) ;
        assign ceo = ce & tc ;
        assign q = sup[4:1] ;

        always @ (posedge clk) begin
                sup[0] <= (r | ceo) ? 0 : ce ? !sup[0] : sup[0] ;
                sup[1] <= (r | ceo) ? 0 : ((sup[0] == 0) & ce) ? !sup[1] : sup[1] ; 
                sup[2] <= (r | ceo) ? 0 : ((sup[1:0] == ((1 << 1) | 1)) & ce) ? !sup[2] : sup[2] ;
                sup[3] <= (r | ceo) ? 0 : ((sup[2:0] == ((1 << 2) | 1)) & ce) ? !sup[3] : sup[3] ;
                sup[4] <= (r | ceo) ? 0 : ((sup[3:0] == ((1 << 3) | 1)) & ce) ? !sup[4] : sup[4] ;
        end

endmodule

src/verilog/counters/VCG4RE/testbench.v
`timescale 1ns / 1ps

module VCG4RE_tb ;

        initial begin
                $dumpfile("data/trace.vcd") ;
                $dumpvars(0, VCG4RE_tb) ;
                #128 $finish ;
        end

        reg clk = 0 ;
        always #1 clk <= !clk ;

        reg [3:0]q ;
        wire tc ;
        wire ceo ;

        VCG4RE counter (
                .clk (clk),
                .ce (1),
                .r (0),
                .tc (tc),
                .ceo (ceo),
                .q (q)
        );

endmodule

src/verilog/counters/VCG4RE/data/trace.vcd
$version Generated by VerilatedVcd $end
$timescale 1ps $end
 $scope module $rootio $end
 $upscope $end
 $scope module VCG4RE_tb $end
  $var wire 1 & clk $end
  $var wire 4 # q [3:0] $end
  $var wire 1 $ tc $end
  $var wire 1 $ ceo $end
  $scope module counter $end
   $var wire 1 & clk $end
   $var wire 1 $ tc $end
   $var wire 1 ' ce $end
   $var wire 1 $ ceo $end
   $var wire 1 ( r $end
   $var wire 4 # q [3:0] $end
   $var wire 5 % sup [4:0] $end
  $upscope $end
 $upscope $end
$enddefinitions $end


#0
b0000 #
0$
b00000 %
0&
1'
0(
#1000
b0001 #
b00011 %
1&
#2000
0&
#3000
b0011 #
b00110 %
1&
#4000
0&
#5000
b0010 #
b00101 %
1&
#6000
0&
#7000
b0110 #
b01100 %
1&
#8000
0&
#9000
b0111 #
b01111 %
1&
#10000
0&
#11000
b0101 #
b01010 %
1&
#12000
0&
#13000
b0100 #
b01001 %
1&
#14000
0&
#15000
b1100 #
b11000 %
1&
#16000
0&
#17000
b1101 #
b11011 %
1&
#18000
0&
#19000
b1111 #
b11110 %
1&
#20000
0&
#21000
b1110 #
b11101 %
1&
#22000
0&
#23000
b1010 #
b10100 %
1&
#24000
0&
#25000
b1011 #
b10111 %
1&
#26000
0&
#27000
b1001 #
b10010 %
1&
#28000
0&
#29000
b1000 #
1$
b10001 %
1&
#30000
0&
#31000
b0000 #
0$
b00000 %
1&
#32000
0&
#33000
b0001 #
b00011 %
1&
#34000
0&
#35000
b0011 #
b00110 %
1&
#36000
0&
#37000
b0010 #
b00101 %
1&
#38000
0&
#39000
b0110 #
b01100 %
1&
#40000
0&
#41000
b0111 #
b01111 %
1&
#42000
0&
#43000
b0101 #
b01010 %
1&
#44000
0&
#45000
b0100 #
b01001 %
1&
#46000
0&
#47000
b1100 #
b11000 %
1&
#48000
0&
#49000
b1101 #
b11011 %
1&
#50000
0&
#51000
b1111 #
b11110 %
1&
#52000
0&
#53000
b1110 #
b11101 %
1&
#54000
0&
#55000
b1010 #
b10100 %
1&
#56000
0&
#57000
b1011 #
b10111 %
1&
#58000
0&
#59000
b1001 #
b10010 %
1&
#60000
0&
#61000
b1000 #
1$
b10001 %
1&
#62000
0&
#63000
b0000 #
0$
b00000 %
1&
#64000
0&
#65000
b0001 #
b00011 %
1&
#66000
0&
#67000
b0011 #
b00110 %
1&
#68000
0&
#69000
b0010 #
b00101 %
1&
#70000
0&
#71000
b0110 #
b01100 %
1&
#72000
0&
#73000
b0111 #
b01111 %
1&
#74000
0&
#75000
b0101 #
b01010 %
1&
#76000
0&
#77000
b0100 #
b01001 %
1&
#78000
0&
#79000
b1100 #
b11000 %
1&
#80000
0&
#81000
b1101 #
b11011 %
1&
#82000
0&
#83000
b1111 #
b11110 %
1&
#84000
0&
#85000
b1110 #
b11101 %
1&
#86000
0&
#87000
b1010 #
b10100 %
1&
#88000
0&
#89000
b1011 #
b10111 %
1&
#90000
0&
#91000
b1001 #
b10010 %
1&
#92000
0&
#93000
b1000 #
1$
b10001 %
1&
#94000
0&
#95000
b0000 #
0$
b00000 %
1&
#96000
0&
#97000
b0001 #
b00011 %
1&
#98000
0&
#99000
b0011 #
b00110 %
1&
#100000
0&
#101000
b0010 #
b00101 %
1&
#102000
0&
#103000
b0110 #
b01100 %
1&
#104000
0&
#105000
b0111 #
b01111 %
1&
#106000
0&
#107000
b0101 #
b01010 %
1&
#108000
0&
#109000
b0100 #
b01001 %
1&
#110000
0&
#111000
b1100 #
b11000 %
1&
#112000
0&
#113000
b1101 #
b11011 %
1&
#114000
0&
#115000
b1111 #
b11110 %
1&
#116000
0&
#117000
b1110 #
b11101 %
1&
#118000
0&
#119000
b1010 #
b10100 %
1&
#120000
0&
#121000
b1011 #
b10111 %
1&
#122000
0&
#123000
b1001 #
b10010 %
1&
#124000
0&
#125000
b1000 #
1$
b10001 %
1&
#126000
0&
#127000
b0000 #
0$
b00000 %
1&
