src/verilog/counters/VCBD4SE/device.v
`define m 4

module VCBDmSE ( input clk, output wire tc,
                 input ce,  output wire ceo,
                 input s,   output reg [`m - 1 : 0]q = (1 << `m) - 1 );
        
        assign tc = (q == 0) ;
        assign ceo = ce & tc ;

        always @ (posedge clk) begin
                q <= s ? ((1 << `m) - 1) : ce ? q - 1 : q ;
        end

endmodule

src/verilog/counters/VCBD4SE/testbench.v
`timescale 1ns / 1ps

module VCBD4SE_tb ;

        initial begin
                $dumpfile("data/trace.vcd") ;
                $dumpvars(0, VCBD4SE_tb) ;
                #64 $finish ;
        end

        reg clk = 0 ;
        always #1 clk = !clk ;

        reg [3:0]q ;
        wire tc ;
        wire ceo ;

        VCBDmSE counter (
                .clk (clk),
                .ce (1),
                .s (0),
                .tc (tc),
                .ceo (ceo),
                .q (q)
        );

endmodule

src/verilog/counters/VCBD4SE/data/trace.vcd
$version Generated by VerilatedVcd $end
$timescale 1ps $end
 $scope module $rootio $end
 $upscope $end
 $scope module VCBD4SE_tb $end
  $var wire 1 # clk $end
  $var wire 4 $ q [3:0] $end
  $var wire 1 % tc $end
  $var wire 1 % ceo $end
  $scope module counter $end
   $var wire 1 # clk $end
   $var wire 1 % tc $end
   $var wire 1 & ce $end
   $var wire 1 % ceo $end
   $var wire 1 ' s $end
   $var wire 4 $ q [3:0] $end
  $upscope $end
 $upscope $end
$enddefinitions $end


#0
0#
b1111 $
0%
1&
0'
#1000
1#
b1110 $
#2000
0#
#3000
1#
b1101 $
#4000
0#
#5000
1#
b1100 $
#6000
0#
#7000
1#
b1011 $
#8000
0#
#9000
1#
b1010 $
#10000
0#
#11000
1#
b1001 $
#12000
0#
#13000
1#
b1000 $
#14000
0#
#15000
1#
b0111 $
#16000
0#
#17000
1#
b0110 $
#18000
0#
#19000
1#
b0101 $
#20000
0#
#21000
1#
b0100 $
#22000
0#
#23000
1#
b0011 $
#24000
0#
#25000
1#
b0010 $
#26000
0#
#27000
1#
b0001 $
#28000
0#
#29000
1#
b0000 $
1%
#30000
0#
#31000
1#
b1111 $
0%
#32000
0#
#33000
1#
b1110 $
#34000
0#
#35000
1#
b1101 $
#36000
0#
#37000
1#
b1100 $
#38000
0#
#39000
1#
b1011 $
#40000
0#
#41000
1#
b1010 $
#42000
0#
#43000
1#
b1001 $
#44000
0#
#45000
1#
b1000 $
#46000
0#
#47000
1#
b0111 $
#48000
0#
#49000
1#
b0110 $
#50000
0#
#51000
1#
b0101 $
#52000
0#
#53000
1#
b0100 $
#54000
0#
#55000
1#
b0011 $
#56000
0#
#57000
1#
b0010 $
#58000
0#
#59000
1#
b0001 $
#60000
0#
#61000
1#
b0000 $
1%
#62000
0#
#63000
1#
b1111 $
0%
