src/verilog/counters/VCD4RE/device.v
module VCDRE ( input clk, output wire tc,
               input ce,  output wire ceo,
               input r,   output reg [3:0]q = 0 );

        assign tc = (q == 9) ;
        assign ceo = ce & tc ;

        always @ (posedge clk) begin
                q <= (r | ceo) ? 0 : ce ? q + 1 : q ;
        end

endmodule

module VCD4RE ( input clk, output wire tc,
                input ce,  output wire ceo,
                input r,   output reg [3:0]q0 = 0,
                           output reg [3:0]q1 = 0,
                           output reg [3:0]q2 = 0,
                           output reg [3:0]q3 = 0 );

        wire tc0, tc1, tc2, tc3 ;
        assign tc = tc0 & tc1 & tc2 & tc3 ;

        wire inter_ceo_01, inter_ceo_12, inter_ceo_23 ;

        VCDRE dec_ctr_0 (
                .clk (clk),
                .ce (ce),
                .r (r),
                .tc (tc0),
                .ceo (inter_ceo_01),
                .q (q0)
        );

        VCDRE dec_ctr_1 (
                .clk (clk),
                .ce (inter_ceo_01),
                .r (r),
                .tc (tc1),
                .ceo (inter_ceo_12),
                .q (q1)
        );

        VCDRE dec_ctr_2 (
                .clk (clk),
                .ce (inter_ceo_12),
                .r (r),
                .tc (tc2),
                .ceo (inter_ceo_23),
                .q (q2)
        );

        VCDRE dec_ctr_3 (
                .clk (clk),
                .ce (inter_ceo_23),
                .r (r),
                .tc (tc3),
                .ceo (ceo),
                .q (q3)
        );

endmodule

src/verilog/counters/VCD4RE/testbench.v
`timescale 1ns / 1ps

module VCD4RE_tb ;

        initial begin
                $dumpfile("data/trace.vcd") ;
                $dumpvars(0, VCD4RE_tb) ;
                #4200 $finish ;
        end

        reg clk = 0 ;
        always #1 clk = !clk ;

        reg [3:0] q[0:3] ;
        wire tc ;
        wire ceo ;

        VCD4RE counter (
                .clk (clk),
                .ce (1),
                .r (0),
                .tc (tc),
                .ceo (ceo),
                .q0 (q[0]),
                .q1 (q[1]),
                .q2 (q[2]),
                .q3 (q[3])
        );

endmodule

src/verilog/counters/waveforms/VCD4RE.vcd
$version Generated by VerilatedVcd $end
$timescale 1ps $end
 $scope module $rootio $end
 $upscope $end
 $scope module VCD4RE_tb $end
  $var wire 1 3 clk $end
  $var wire 4 # q[0] [3:0] $end
  $var wire 4 $ q[1] [3:0] $end
  $var wire 4 % q[2] [3:0] $end
  $var wire 4 & q[3] [3:0] $end
  $var wire 1 ' tc $end
  $var wire 1 ( ceo $end
  $scope module counter $end
   $var wire 1 3 clk $end
   $var wire 1 ' tc $end
   $var wire 1 4 ce $end
   $var wire 1 ( ceo $end
   $var wire 1 5 r $end
   $var wire 4 ) q0 [3:0] $end
   $var wire 4 * q1 [3:0] $end
   $var wire 4 + q2 [3:0] $end
   $var wire 4 , q3 [3:0] $end
   $var wire 1 - tc0 $end
   $var wire 1 . tc1 $end
   $var wire 1 / tc2 $end
   $var wire 1 0 tc3 $end
   $var wire 1 - inter_ceo_01 $end
   $var wire 1 1 inter_ceo_12 $end
   $var wire 1 2 inter_ceo_23 $end
   $scope module dec_ctr_0 $end
    $var wire 1 3 clk $end
    $var wire 1 - tc $end
    $var wire 1 4 ce $end
    $var wire 1 - ceo $end
    $var wire 1 5 r $end
    $var wire 4 ) q [3:0] $end
   $upscope $end
   $scope module dec_ctr_1 $end
    $var wire 1 3 clk $end
    $var wire 1 . tc $end
    $var wire 1 - ce $end
    $var wire 1 1 ceo $end
    $var wire 1 5 r $end
    $var wire 4 * q [3:0] $end
   $upscope $end
   $scope module dec_ctr_2 $end
    $var wire 1 3 clk $end
    $var wire 1 / tc $end
    $var wire 1 1 ce $end
    $var wire 1 2 ceo $end
    $var wire 1 5 r $end
    $var wire 4 + q [3:0] $end
   $upscope $end
   $scope module dec_ctr_3 $end
    $var wire 1 3 clk $end
    $var wire 1 0 tc $end
    $var wire 1 2 ce $end
    $var wire 1 ( ceo $end
    $var wire 1 5 r $end
    $var wire 4 , q [3:0] $end
   $upscope $end
  $upscope $end
 $upscope $end
$enddefinitions $end


#0
b0000 #
b0000 $
b0000 %
b0000 &
0'
0(
b0000 )
b0000 *
b0000 +
b0000 ,
0-
0.
0/
00
01
02
03
14
05
#1000
b0001 #
b0001 )
13
#2000
03
#3000
b0010 #
b0010 )
13
#4000
03
#5000
b0011 #
b0011 )
13
#6000
03
#7000
b0100 #
b0100 )
13
#8000
03
#9000
b0101 #
b0101 )
13
#10000
03
#11000
b0110 #
b0110 )
13
#12000
03
#13000
b0111 #
b0111 )
13
#14000
03
#15000
b1000 #
b1000 )
13
#16000
03
#17000
b1001 #
b1001 )
1-
13
#18000
03
#19000
b0000 #
b0001 $
b0000 )
b0001 *
0-
13
#20000
03
#21000
b0001 #
b0001 )
13
#22000
03
#23000
b0010 #
b0010 )
13
#24000
03
#25000
b0011 #
b0011 )
13
#26000
03
#27000
b0100 #
b0100 )
13
#28000
03
#29000
b0101 #
b0101 )
13
#30000
03
#31000
b0110 #
b0110 )
13
#32000
03
#33000
b0111 #
b0111 )
13
#34000
03
#35000
b1000 #
b1000 )
13
#36000
03
#37000
b1001 #
b1001 )
1-
13
#38000
03
#39000
b0000 #
b0010 $
b0000 )
b0010 *
0-
13
#40000
03
#41000
b0001 #
b0001 )
13
#42000
03
#43000
b0010 #
b0010 )
13
#44000
03
#45000
b0011 #
b0011 )
13
#46000
03
#47000
b0100 #
b0100 )
13
#48000
03
#49000
b0101 #
b0101 )
13
#50000
03
#51000
b0110 #
b0110 )
13
#52000
03
#53000
b0111 #
b0111 )
13
#54000
03
#55000
b1000 #
b1000 )
13
#56000
03
#57000
b1001 #
b1001 )
1-
13
#58000
03
#59000
b0000 #
b0011 $
b0000 )
b0011 *
0-
13
#60000
03
#61000
b0001 #
b0001 )
13
#62000
03
#63000
b0010 #
b0010 )
13
#64000
03
#65000
b0011 #
b0011 )
13
#66000
03
#67000
b0100 #
b0100 )
13
#68000
03
#69000
b0101 #
b0101 )
13
#70000
03
#71000
b0110 #
b0110 )
13
#72000
03
#73000
b0111 #
b0111 )
13
#74000
03
#75000
b1000 #
b1000 )
13
#76000
03
#77000
b1001 #
b1001 )
1-
13
#78000
03
#79000
b0000 #
b0100 $
b0000 )
b0100 *
0-
13
#80000
03
#81000
b0001 #
b0001 )
13
#82000
03
#83000
b0010 #
b0010 )
13
#84000
03
#85000
b0011 #
b0011 )
13
#86000
03
#87000
b0100 #
b0100 )
13
#88000
03
#89000
b0101 #
b0101 )
13
#90000
03
#91000
b0110 #
b0110 )
13
#92000
03
#93000
b0111 #
b0111 )
13
#94000
03
#95000
b1000 #
b1000 )
13
#96000
03
#97000
b1001 #
b1001 )
1-
13
#98000
03
#99000
b0000 #
b0101 $
b0000 )
b0101 *
0-
13
#100000
03
#101000
b0001 #
b0001 )
13
#102000
03
#103000
b0010 #
b0010 )
13
#104000
03
#105000
b0011 #
b0011 )
13
#106000
03
#107000
b0100 #
b0100 )
13
#108000
03
#109000
b0101 #
b0101 )
13
#110000
03
#111000
b0110 #
b0110 )
13
#112000
03
#113000
b0111 #
b0111 )
13
#114000
03
#115000
b1000 #
b1000 )
13
#116000
03
#117000
b1001 #
b1001 )
1-
13
#118000
03
#119000
b0000 #
b0110 $
b0000 )
b0110 *
0-
13
#120000
03
#121000
b0001 #
b0001 )
13
#122000
03
#123000
b0010 #
b0010 )
13
#124000
03
#125000
b0011 #
b0011 )
13
#126000
03
#127000
b0100 #
b0100 )
13
#128000
03
#129000
b0101 #
b0101 )
13
#130000
03
#131000
b0110 #
b0110 )
13
#132000
03
#133000
b0111 #
b0111 )
13
#134000
03
#135000
b1000 #
b1000 )
13
#136000
03
#137000
b1001 #
b1001 )
1-
13
#138000
03
#139000
b0000 #
b0111 $
b0000 )
b0111 *
0-
13
#140000
03
#141000
b0001 #
b0001 )
13
#142000
03
#143000
b0010 #
b0010 )
13
#144000
03
#145000
b0011 #
b0011 )
13
#146000
03
#147000
b0100 #
b0100 )
13
#148000
03
#149000
b0101 #
b0101 )
13
#150000
03
#151000
b0110 #
b0110 )
13
#152000
03
#153000
b0111 #
b0111 )
13
#154000
03
#155000
b1000 #
b1000 )
13
#156000
03
#157000
b1001 #
b1001 )
1-
13
#158000
03
#159000
b0000 #
b1000 $
b0000 )
b1000 *
0-
13
#160000
03
#161000
b0001 #
b0001 )
13
#162000
03
#163000
b0010 #
b0010 )
13
#164000
03
#165000
b0011 #
b0011 )
13
#166000
03
#167000
b0100 #
b0100 )
13
#168000
03
#169000
b0101 #
b0101 )
13
#170000
03
#171000
b0110 #
b0110 )
13
#172000
03
#173000
b0111 #
b0111 )
13
#174000
03
#175000
b1000 #
b1000 )
13
#176000
03
#177000
b1001 #
b1001 )
1-
13
#178000
03
#179000
b0000 #
b1001 $
b0000 )
b1001 *
0-
1.
13
#180000
03
#181000
b0001 #
b0001 )
13
#182000
03
#183000
b0010 #
b0010 )
13
#184000
03
#185000
b0011 #
b0011 )
13
#186000
03
#187000
b0100 #
b0100 )
13
#188000
03
#189000
b0101 #
b0101 )
13
#190000
03
#191000
b0110 #
b0110 )
13
#192000
03
#193000
b0111 #
b0111 )
13
#194000
03
#195000
b1000 #
b1000 )
13
#196000
03
#197000
b1001 #
b1001 )
1-
11
13
#198000
03
#199000
b0000 #
b0000 $
b0001 %
b0000 )
b0000 *
b0001 +
0-
0.
01
13
#200000
03
#201000
b0001 #
b0001 )
13
#202000
03
#203000
b0010 #
b0010 )
13
#204000
03
#205000
b0011 #
b0011 )
13
#206000
03
#207000
b0100 #
b0100 )
13
#208000
03
#209000
b0101 #
b0101 )
13
#210000
03
#211000
b0110 #
b0110 )
13
#212000
03
#213000
b0111 #
b0111 )
13
#214000
03
#215000
b1000 #
b1000 )
13
#216000
03
#217000
b1001 #
b1001 )
1-
13
#218000
03
#219000
b0000 #
b0001 $
b0000 )
b0001 *
0-
13
#220000
03
#221000
b0001 #
b0001 )
13
#222000
03
#223000
b0010 #
b0010 )
13
#224000
03
#225000
b0011 #
b0011 )
13
#226000
03
#227000
b0100 #
b0100 )
13
#228000
03
#229000
b0101 #
b0101 )
13
#230000
03
#231000
b0110 #
b0110 )
13
#232000
03
#233000
b0111 #
b0111 )
13
#234000
03
#235000
b1000 #
b1000 )
13
#236000
03
#237000
b1001 #
b1001 )
1-
13
#238000
03
#239000
b0000 #
b0010 $
b0000 )
b0010 *
0-
13
#240000
03
#241000
b0001 #
b0001 )
13
#242000
03
#243000
b0010 #
b0010 )
13
#244000
03
#245000
b0011 #
b0011 )
13
#246000
03
#247000
b0100 #
b0100 )
13
#248000
03
#249000
b0101 #
b0101 )
13
#250000
03
#251000
b0110 #
b0110 )
13
#252000
03
#253000
b0111 #
b0111 )
13
#254000
03
#255000
b1000 #
b1000 )
13
#256000
03
#257000
b1001 #
b1001 )
1-
13
#258000
03
#259000
b0000 #
b0011 $
b0000 )
b0011 *
0-
13
#260000
03
#261000
b0001 #
b0001 )
13
#262000
03
#263000
b0010 #
b0010 )
13
#264000
03
#265000
b0011 #
b0011 )
13
#266000
03
#267000
b0100 #
b0100 )
13
#268000
03
#269000
b0101 #
b0101 )
13
#270000
03
#271000
b0110 #
b0110 )
13
#272000
03
#273000
b0111 #
b0111 )
13
#274000
03
#275000
b1000 #
b1000 )
13
#276000
03
#277000
b1001 #
b1001 )
1-
13
#278000
03
#279000
b0000 #
b0100 $
b0000 )
b0100 *
0-
13
#280000
03
#281000
b0001 #
b0001 )
13
#282000
03
#283000
b0010 #
b0010 )
13
#284000
03
#285000
b0011 #
b0011 )
13
#286000
03
#287000
b0100 #
b0100 )
13
#288000
03
#289000
b0101 #
b0101 )
13
#290000
03
#291000
b0110 #
b0110 )
13
#292000
03
#293000
b0111 #
b0111 )
13
#294000
03
#295000
b1000 #
b1000 )
13
#296000
03
#297000
b1001 #
b1001 )
1-
13
#298000
03
#299000
b0000 #
b0101 $
b0000 )
b0101 *
0-
13
#300000
03
#301000
b0001 #
b0001 )
13
#302000
03
#303000
b0010 #
b0010 )
13
#304000
03
#305000
b0011 #
b0011 )
13
#306000
03
#307000
b0100 #
b0100 )
13
#308000
03
#309000
b0101 #
b0101 )
13
#310000
03
#311000
b0110 #
b0110 )
13
#312000
03
#313000
b0111 #
b0111 )
13
#314000
03
#315000
b1000 #
b1000 )
13
#316000
03
#317000
b1001 #
b1001 )
1-
13
#318000
03
#319000
b0000 #
b0110 $
b0000 )
b0110 *
0-
13
#320000
03
#321000
b0001 #
b0001 )
13
#322000
03
#323000
b0010 #
b0010 )
13
#324000
03
#325000
b0011 #
b0011 )
13
#326000
03
#327000
b0100 #
b0100 )
13
#328000
03
#329000
b0101 #
b0101 )
13
#330000
03
#331000
b0110 #
b0110 )
13
#332000
03
#333000
b0111 #
b0111 )
13
#334000
03
#335000
b1000 #
b1000 )
13
#336000
03
#337000
b1001 #
b1001 )
1-
13
#338000
03
#339000
b0000 #
b0111 $
b0000 )
b0111 *
0-
13
#340000
03
#341000
b0001 #
b0001 )
13
#342000
03
#343000
b0010 #
b0010 )
13
#344000
03
#345000
b0011 #
b0011 )
13
#346000
03
#347000
b0100 #
b0100 )
13
#348000
03
#349000
b0101 #
b0101 )
13
#350000
03
#351000
b0110 #
b0110 )
13
#352000
03
#353000
b0111 #
b0111 )
13
#354000
03
#355000
b1000 #
b1000 )
13
#356000
03
#357000
b1001 #
b1001 )
1-
13
#358000
03
#359000
b0000 #
b1000 $
b0000 )
b1000 *
0-
13
#360000
03
#361000
b0001 #
b0001 )
13
#362000
03
#363000
b0010 #
b0010 )
13
#364000
03
#365000
b0011 #
b0011 )
13
#366000
03
#367000
b0100 #
b0100 )
13
#368000
03
#369000
b0101 #
b0101 )
13
#370000
03
#371000
b0110 #
b0110 )
13
#372000
03
#373000
b0111 #
b0111 )
13
#374000
03
#375000
b1000 #
b1000 )
13
#376000
03
#377000
b1001 #
b1001 )
1-
13
#378000
03
#379000
b0000 #
b1001 $
b0000 )
b1001 *
0-
1.
13
#380000
03
#381000
b0001 #
b0001 )
13
#382000
03
#383000
b0010 #
b0010 )
13
#384000
03
#385000
b0011 #
b0011 )
13
#386000
03
#387000
b0100 #
b0100 )
13
#388000
03
#389000
b0101 #
b0101 )
13
#390000
03
#391000
b0110 #
b0110 )
13
#392000
03
#393000
b0111 #
b0111 )
13
#394000
03
#395000
b1000 #
b1000 )
13
#396000
03
#397000
b1001 #
b1001 )
1-
11
13
#398000
03
#399000
b0000 #
b0000 $
b0010 %
b0000 )
b0000 *
b0010 +
0-
0.
01
13
#400000
03
#401000
b0001 #
b0001 )
13
#402000
03
#403000
b0010 #
b0010 )
13
#404000
03
#405000
b0011 #
b0011 )
13
#406000
03
#407000
b0100 #
b0100 )
13
#408000
03
#409000
b0101 #
b0101 )
13
#410000
03
#411000
b0110 #
b0110 )
13
#412000
03
#413000
b0111 #
b0111 )
13
#414000
03
#415000
b1000 #
b1000 )
13
#416000
03
#417000
b1001 #
b1001 )
1-
13
#418000
03
#419000
b0000 #
b0001 $
b0000 )
b0001 *
0-
13
#420000
03
#421000
b0001 #
b0001 )
13
#422000
03
#423000
b0010 #
b0010 )
13
#424000
03
#425000
b0011 #
b0011 )
13
#426000
03
#427000
b0100 #
b0100 )
13
#428000
03
#429000
b0101 #
b0101 )
13
#430000
03
#431000
b0110 #
b0110 )
13
#432000
03
#433000
b0111 #
b0111 )
13
#434000
03
#435000
b1000 #
b1000 )
13
#436000
03
#437000
b1001 #
b1001 )
1-
13
#438000
03
#439000
b0000 #
b0010 $
b0000 )
b0010 *
0-
13
#440000
03
#441000
b0001 #
b0001 )
13
#442000
03
#443000
b0010 #
b0010 )
13
#444000
03
#445000
b0011 #
b0011 )
13
#446000
03
#447000
b0100 #
b0100 )
13
#448000
03
#449000
b0101 #
b0101 )
13
#450000
03
#451000
b0110 #
b0110 )
13
#452000
03
#453000
b0111 #
b0111 )
13
#454000
03
#455000
b1000 #
b1000 )
13
#456000
03
#457000
b1001 #
b1001 )
1-
13
#458000
03
#459000
b0000 #
b0011 $
b0000 )
b0011 *
0-
13
#460000
03
#461000
b0001 #
b0001 )
13
#462000
03
#463000
b0010 #
b0010 )
13
#464000
03
#465000
b0011 #
b0011 )
13
#466000
03
#467000
b0100 #
b0100 )
13
#468000
03
#469000
b0101 #
b0101 )
13
#470000
03
#471000
b0110 #
b0110 )
13
#472000
03
#473000
b0111 #
b0111 )
13
#474000
03
#475000
b1000 #
b1000 )
13
#476000
03
#477000
b1001 #
b1001 )
1-
13
#478000
03
#479000
b0000 #
b0100 $
b0000 )
b0100 *
0-
13
#480000
03
#481000
b0001 #
b0001 )
13
#482000
03
#483000
b0010 #
b0010 )
13
#484000
03
#485000
b0011 #
b0011 )
13
#486000
03
#487000
b0100 #
b0100 )
13
#488000
03
#489000
b0101 #
b0101 )
13
#490000
03
#491000
b0110 #
b0110 )
13
#492000
03
#493000
b0111 #
b0111 )
13
#494000
03
#495000
b1000 #
b1000 )
13
#496000
03
#497000
b1001 #
b1001 )
1-
13
#498000
03
#499000
b0000 #
b0101 $
b0000 )
b0101 *
0-
13
#500000
03
#501000
b0001 #
b0001 )
13
#502000
03
#503000
b0010 #
b0010 )
13
#504000
03
#505000
b0011 #
b0011 )
13
#506000
03
#507000
b0100 #
b0100 )
13
#508000
03
#509000
b0101 #
b0101 )
13
#510000
03
#511000
b0110 #
b0110 )
13
#512000
03
#513000
b0111 #
b0111 )
13
#514000
03
#515000
b1000 #
b1000 )
13
#516000
03
#517000
b1001 #
b1001 )
1-
13
#518000
03
#519000
b0000 #
b0110 $
b0000 )
b0110 *
0-
13
#520000
03
#521000
b0001 #
b0001 )
13
#522000
03
#523000
b0010 #
b0010 )
13
#524000
03
#525000
b0011 #
b0011 )
13
#526000
03
#527000
b0100 #
b0100 )
13
#528000
03
#529000
b0101 #
b0101 )
13
#530000
03
#531000
b0110 #
b0110 )
13
#532000
03
#533000
b0111 #
b0111 )
13
#534000
03
#535000
b1000 #
b1000 )
13
#536000
03
#537000
b1001 #
b1001 )
1-
13
#538000
03
#539000
b0000 #
b0111 $
b0000 )
b0111 *
0-
13
#540000
03
#541000
b0001 #
b0001 )
13
#542000
03
#543000
b0010 #
b0010 )
13
#544000
03
#545000
b0011 #
b0011 )
13
#546000
03
#547000
b0100 #
b0100 )
13
#548000
03
#549000
b0101 #
b0101 )
13
#550000
03
#551000
b0110 #
b0110 )
13
#552000
03
#553000
b0111 #
b0111 )
13
#554000
03
#555000
b1000 #
b1000 )
13
#556000
03
#557000
b1001 #
b1001 )
1-
13
#558000
03
#559000
b0000 #
b1000 $
b0000 )
b1000 *
0-
13
#560000
03
#561000
b0001 #
b0001 )
13
#562000
03
#563000
b0010 #
b0010 )
13
#564000
03
#565000
b0011 #
b0011 )
13
#566000
03
#567000
b0100 #
b0100 )
13
#568000
03
#569000
b0101 #
b0101 )
13
#570000
03
#571000
b0110 #
b0110 )
13
#572000
03
#573000
b0111 #
b0111 )
13
#574000
03
#575000
b1000 #
b1000 )
13
#576000
03
#577000
b1001 #
b1001 )
1-
13
#578000
03
#579000
b0000 #
b1001 $
b0000 )
b1001 *
0-
1.
13
#580000
03
#581000
b0001 #
b0001 )
13
#582000
03
#583000
b0010 #
b0010 )
13
#584000
03
#585000
b0011 #
b0011 )
13
#586000
03
#587000
b0100 #
b0100 )
13
#588000
03
#589000
b0101 #
b0101 )
13
#590000
03
#591000
b0110 #
b0110 )
13
#592000
03
#593000
b0111 #
b0111 )
13
#594000
03
#595000
b1000 #
b1000 )
13
#596000
03
#597000
b1001 #
b1001 )
1-
11
13
#598000
03
#599000
b0000 #
b0000 $
b0011 %
b0000 )
b0000 *
b0011 +
0-
0.
01
13
#600000
03
#601000
b0001 #
b0001 )
13
#602000
03
#603000
b0010 #
b0010 )
13
#604000
03
#605000
b0011 #
b0011 )
13
#606000
03
#607000
b0100 #
b0100 )
13
#608000
03
#609000
b0101 #
b0101 )
13
#610000
03
#611000
b0110 #
b0110 )
13
#612000
03
#613000
b0111 #
b0111 )
13
#614000
03
#615000
b1000 #
b1000 )
13
#616000
03
#617000
b1001 #
b1001 )
1-
13
#618000
03
#619000
b0000 #
b0001 $
b0000 )
b0001 *
0-
13
#620000
03
#621000
b0001 #
b0001 )
13
#622000
03
#623000
b0010 #
b0010 )
13
#624000
03
#625000
b0011 #
b0011 )
13
#626000
03
#627000
b0100 #
b0100 )
13
#628000
03
#629000
b0101 #
b0101 )
13
#630000
03
#631000
b0110 #
b0110 )
13
#632000
03
#633000
b0111 #
b0111 )
13
#634000
03
#635000
b1000 #
b1000 )
13
#636000
03
#637000
b1001 #
b1001 )
1-
13
#638000
03
#639000
b0000 #
b0010 $
b0000 )
b0010 *
0-
13
#640000
03
#641000
b0001 #
b0001 )
13
#642000
03
#643000
b0010 #
b0010 )
13
#644000
03
#645000
b0011 #
b0011 )
13
#646000
03
#647000
b0100 #
b0100 )
13
#648000
03
#649000
b0101 #
b0101 )
13
#650000
03
#651000
b0110 #
b0110 )
13
#652000
03
#653000
b0111 #
b0111 )
13
#654000
03
#655000
b1000 #
b1000 )
13
#656000
03
#657000
b1001 #
b1001 )
1-
13
#658000
03
#659000
b0000 #
b0011 $
b0000 )
b0011 *
0-
13
#660000
03
#661000
b0001 #
b0001 )
13
#662000
03
#663000
b0010 #
b0010 )
13
#664000
03
#665000
b0011 #
b0011 )
13
#666000
03
#667000
b0100 #
b0100 )
13
#668000
03
#669000
b0101 #
b0101 )
13
#670000
03
#671000
b0110 #
b0110 )
13
#672000
03
#673000
b0111 #
b0111 )
13
#674000
03
#675000
b1000 #
b1000 )
13
#676000
03
#677000
b1001 #
b1001 )
1-
13
#678000
03
#679000
b0000 #
b0100 $
b0000 )
b0100 *
0-
13
#680000
03
#681000
b0001 #
b0001 )
13
#682000
03
#683000
b0010 #
b0010 )
13
#684000
03
#685000
b0011 #
b0011 )
13
#686000
03
#687000
b0100 #
b0100 )
13
#688000
03
#689000
b0101 #
b0101 )
13
#690000
03
#691000
b0110 #
b0110 )
13
#692000
03
#693000
b0111 #
b0111 )
13
#694000
03
#695000
b1000 #
b1000 )
13
#696000
03
#697000
b1001 #
b1001 )
1-
13
#698000
03
#699000
b0000 #
b0101 $
b0000 )
b0101 *
0-
13
#700000
03
#701000
b0001 #
b0001 )
13
#702000
03
#703000
b0010 #
b0010 )
13
#704000
03
#705000
b0011 #
b0011 )
13
#706000
03
#707000
b0100 #
b0100 )
13
#708000
03
#709000
b0101 #
b0101 )
13
#710000
03
#711000
b0110 #
b0110 )
13
#712000
03
#713000
b0111 #
b0111 )
13
#714000
03
#715000
b1000 #
b1000 )
13
#716000
03
#717000
b1001 #
b1001 )
1-
13
#718000
03
#719000
b0000 #
b0110 $
b0000 )
b0110 *
0-
13
#720000
03
#721000
b0001 #
b0001 )
13
#722000
03
#723000
b0010 #
b0010 )
13
#724000
03
#725000
b0011 #
b0011 )
13
#726000
03
#727000
b0100 #
b0100 )
13
#728000
03
#729000
b0101 #
b0101 )
13
#730000
03
#731000
b0110 #
b0110 )
13
#732000
03
#733000
b0111 #
b0111 )
13
#734000
03
#735000
b1000 #
b1000 )
13
#736000
03
#737000
b1001 #
b1001 )
1-
13
#738000
03
#739000
b0000 #
b0111 $
b0000 )
b0111 *
0-
13
#740000
03
#741000
b0001 #
b0001 )
13
#742000
03
#743000
b0010 #
b0010 )
13
#744000
03
#745000
b0011 #
b0011 )
13
#746000
03
#747000
b0100 #
b0100 )
13
#748000
03
#749000
b0101 #
b0101 )
13
#750000
03
#751000
b0110 #
b0110 )
13
#752000
03
#753000
b0111 #
b0111 )
13
#754000
03
#755000
b1000 #
b1000 )
13
#756000
03
#757000
b1001 #
b1001 )
1-
13
#758000
03
#759000
b0000 #
b1000 $
b0000 )
b1000 *
0-
13
#760000
03
#761000
b0001 #
b0001 )
13
#762000
03
#763000
b0010 #
b0010 )
13
#764000
03
#765000
b0011 #
b0011 )
13
#766000
03
#767000
b0100 #
b0100 )
13
#768000
03
#769000
b0101 #
b0101 )
13
#770000
03
#771000
b0110 #
b0110 )
13
#772000
03
#773000
b0111 #
b0111 )
13
#774000
03
#775000
b1000 #
b1000 )
13
#776000
03
#777000
b1001 #
b1001 )
1-
13
#778000
03
#779000
b0000 #
b1001 $
b0000 )
b1001 *
0-
1.
13
#780000
03
#781000
b0001 #
b0001 )
13
#782000
03
#783000
b0010 #
b0010 )
13
#784000
03
#785000
b0011 #
b0011 )
13
#786000
03
#787000
b0100 #
b0100 )
13
#788000
03
#789000
b0101 #
b0101 )
13
#790000
03
#791000
b0110 #
b0110 )
13
#792000
03
#793000
b0111 #
b0111 )
13
#794000
03
#795000
b1000 #
b1000 )
13
#796000
03
#797000
b1001 #
b1001 )
1-
11
13
#798000
03
#799000
b0000 #
b0000 $
b0100 %
b0000 )
b0000 *
b0100 +
0-
0.
01
13
#800000
03
#801000
b0001 #
b0001 )
13
#802000
03
#803000
b0010 #
b0010 )
13
#804000
03
#805000
b0011 #
b0011 )
13
#806000
03
#807000
b0100 #
b0100 )
13
#808000
03
#809000
b0101 #
b0101 )
13
#810000
03
#811000
b0110 #
b0110 )
13
#812000
03
#813000
b0111 #
b0111 )
13
#814000
03
#815000
b1000 #
b1000 )
13
#816000
03
#817000
b1001 #
b1001 )
1-
13
#818000
03
#819000
b0000 #
b0001 $
b0000 )
b0001 *
0-
13
#820000
03
#821000
b0001 #
b0001 )
13
#822000
03
#823000
b0010 #
b0010 )
13
#824000
03
#825000
b0011 #
b0011 )
13
#826000
03
#827000
b0100 #
b0100 )
13
#828000
03
#829000
b0101 #
b0101 )
13
#830000
03
#831000
b0110 #
b0110 )
13
#832000
03
#833000
b0111 #
b0111 )
13
#834000
03
#835000
b1000 #
b1000 )
13
#836000
03
#837000
b1001 #
b1001 )
1-
13
#838000
03
#839000
b0000 #
b0010 $
b0000 )
b0010 *
0-
13
#840000
03
#841000
b0001 #
b0001 )
13
#842000
03
#843000
b0010 #
b0010 )
13
#844000
03
#845000
b0011 #
b0011 )
13
#846000
03
#847000
b0100 #
b0100 )
13
#848000
03
#849000
b0101 #
b0101 )
13
#850000
03
#851000
b0110 #
b0110 )
13
#852000
03
#853000
b0111 #
b0111 )
13
#854000
03
#855000
b1000 #
b1000 )
13
#856000
03
#857000
b1001 #
b1001 )
1-
13
#858000
03
#859000
b0000 #
b0011 $
b0000 )
b0011 *
0-
13
#860000
03
#861000
b0001 #
b0001 )
13
#862000
03
#863000
b0010 #
b0010 )
13
#864000
03
#865000
b0011 #
b0011 )
13
#866000
03
#867000
b0100 #
b0100 )
13
#868000
03
#869000
b0101 #
b0101 )
13
#870000
03
#871000
b0110 #
b0110 )
13
#872000
03
#873000
b0111 #
b0111 )
13
#874000
03
#875000
b1000 #
b1000 )
13
#876000
03
#877000
b1001 #
b1001 )
1-
13
#878000
03
#879000
b0000 #
b0100 $
b0000 )
b0100 *
0-
13
#880000
03
#881000
b0001 #
b0001 )
13
#882000
03
#883000
b0010 #
b0010 )
13
#884000
03
#885000
b0011 #
b0011 )
13
#886000
03
#887000
b0100 #
b0100 )
13
#888000
03
#889000
b0101 #
b0101 )
13
#890000
03
#891000
b0110 #
b0110 )
13
#892000
03
#893000
b0111 #
b0111 )
13
#894000
03
#895000
b1000 #
b1000 )
13
#896000
03
#897000
b1001 #
b1001 )
1-
13
#898000
03
#899000
b0000 #
b0101 $
b0000 )
b0101 *
0-
13
#900000
03
#901000
b0001 #
b0001 )
13
#902000
03
#903000
b0010 #
b0010 )
13
#904000
03
#905000
b0011 #
b0011 )
13
#906000
03
#907000
b0100 #
b0100 )
13
#908000
03
#909000
b0101 #
b0101 )
13
#910000
03
#911000
b0110 #
b0110 )
13
#912000
03
#913000
b0111 #
b0111 )
13
#914000
03
#915000
b1000 #
b1000 )
13
#916000
03
#917000
b1001 #
b1001 )
1-
13
#918000
03
#919000
b0000 #
b0110 $
b0000 )
b0110 *
0-
13
#920000
03
#921000
b0001 #
b0001 )
13
#922000
03
#923000
b0010 #
b0010 )
13
#924000
03
#925000
b0011 #
b0011 )
13
#926000
03
#927000
b0100 #
b0100 )
13
#928000
03
#929000
b0101 #
b0101 )
13
#930000
03
#931000
b0110 #
b0110 )
13
#932000
03
#933000
b0111 #
b0111 )
13
#934000
03
#935000
b1000 #
b1000 )
13
#936000
03
#937000
b1001 #
b1001 )
1-
13
#938000
03
#939000
b0000 #
b0111 $
b0000 )
b0111 *
0-
13
#940000
03
#941000
b0001 #
b0001 )
13
#942000
03
#943000
b0010 #
b0010 )
13
#944000
03
#945000
b0011 #
b0011 )
13
#946000
03
#947000
b0100 #
b0100 )
13
#948000
03
#949000
b0101 #
b0101 )
13
#950000
03
#951000
b0110 #
b0110 )
13
#952000
03
#953000
b0111 #
b0111 )
13
#954000
03
#955000
b1000 #
b1000 )
13
#956000
03
#957000
b1001 #
b1001 )
1-
13
#958000
03
#959000
b0000 #
b1000 $
b0000 )
b1000 *
0-
13
#960000
03
#961000
b0001 #
b0001 )
13
#962000
03
#963000
b0010 #
b0010 )
13
#964000
03
#965000
b0011 #
b0011 )
13
#966000
03
#967000
b0100 #
b0100 )
13
#968000
03
#969000
b0101 #
b0101 )
13
#970000
03
#971000
b0110 #
b0110 )
13
#972000
03
#973000
b0111 #
b0111 )
13
#974000
03
#975000
b1000 #
b1000 )
13
#976000
03
#977000
b1001 #
b1001 )
1-
13
#978000
03
#979000
b0000 #
b1001 $
b0000 )
b1001 *
0-
1.
13
#980000
03
#981000
b0001 #
b0001 )
13
#982000
03
#983000
b0010 #
b0010 )
13
#984000
03
#985000
b0011 #
b0011 )
13
#986000
03
#987000
b0100 #
b0100 )
13
#988000
03
#989000
b0101 #
b0101 )
13
#990000
03
#991000
b0110 #
b0110 )
13
#992000
03
#993000
b0111 #
b0111 )
13
#994000
03
#995000
b1000 #
b1000 )
13
#996000
03
